Workbook

Sheet README
A1: PRECIPICE ECONOMY MODEL — companion to PRECIPICE_GAME_DESIGN_v4.6.md; per-compound content lives in PRECIPICE_COMPOUND_DATABASE.xlsx (58-point cross-verification passed at v4.4)
A3: PURPOSE: validates every §30-flagged parameter before implementation. Tuning_Flags is the conclusions sheet — read it first.
A5: COLOR CODE (industry standard): BLUE = tunable input. BLACK = formula. GREEN = cross-sheet link. Yellow fill = needs doc amendment. Red fill = change recommended.
A7: SHEETS:
A8: Params — every assumption in one place. Change blue cells; the whole model recalculates.
A9: Tiers — doc §5/§10/§15 constants + the monotonic per-slot-hour check (the rule that killed v3's rank math).
A10: Rank_Model — the core: session-based 120-day progression. Era completions/day derive from a 3-login schedule with input-chain limits (a player CANNOT run 12-min timers offline; the model accounts for slot idle time, chain feeding, and market-assisted input buying from T4 era). N5 = sensitivity multiplier.
A11: Prestige_Pacing — per-level run length vs the 120-day commitment. Contains the model's one RED finding.
A12: Player_Economy — per-era daily Pellet flow for the dedicated archetype.
A13: Game_Economy — faucet/sink at 1k/10k/100k DAU with the honest structural-surplus conclusion.
A14: Discovery_Costs — brute-force mapping cost per bracket (answers the T3-cheapness question: validated fine).
A15: Exotic_Decay — the 0.97 curve, floor verification against the doc's run-24 claim.
... A29: MODEL HONESTY: era completion rates are derived estimates (chain math + session schedule), not telemetry. The ±20% sensitivity band (Rank_Model N5) is the honest error bar. Every conclusion that survives both ends of the band is stated as PASS; P7's verdict flips only above 700k/day endgame income, which is why it is flagged rather than silently 'fixed'.

Sheet Params
A1: PRECIPICE ECONOMY MODEL — CENTRAL PARAMETERS (all blue cells are tunable inputs)
A2: Source: PRECIPICE_GAME_DESIGN_v4.6.md. Change blue cells; every other sheet recalculates.
A4: Rank score per natural completion (doc §18) | F4: Other rank sources (doc §18) | K4: Economy constants
A5: Tier | B5: Rank/completion | C5: Slot-hours/run (offline pace) | D5: Pts per slot-hour (OFFLINE pace; doc §18 quotes online — see Tiers col M) | F5: Contracts/day (all 5, blended) | G5: 350 | K5: Exotic decay per unit | L5: 0.97
A6: T1 (extraction) | B6: 0 | C6: 0.041666667 | D6: =IF(C6=0,0,B6/C6) -> 0 | F6: Market sales rank cap/day | G6: 1000 | K6: Exotic floor (frac of initial) | L6: 0.25
A7: T2 | B7: 3 | C7: 0.25 | D7: =IF(C7=0,0,B7/C7) -> 12 | F7: Vault contribution cap/day | G7: 500 | K7: Market sale fee | L7: 0.05
A8: T3 | B8: 16 | C8: 0.9375 | D8: =IF(C8=0,0,B8/C8) -> 17.066667 | F8: Patent claim (once ever) | G8: 500 | K8: Listing fee | L8: 0.01
A9: T4 | B9: 85 | C9: 3.75 | D9: =IF(C9=0,0,B9/C9) -> 22.666667 | F9: Defense T2 | G9: 25 | K9: Online speed bonus | L9: 0.2
A10: T5 | B10: 300 | C10: 10 | D10: =IF(C10=0,0,B10/C10) -> 30 | F10: Defense T3 | G10: 50 | K10: Offline slowdown (x duration) | L10: 1.25
A11: T6 | B11: 1150 | C11: 24 | D11: =IF(C11=0,0,B11/C11) -> 47.916667 | F11: Defense T4 | G11: 100 | K11: Offline income cap base (h) | L11: 12
A12: T7 Exotic | B12: 1500 | C12: 24 | D12: =IF(C12=0,0,B12/C12) -> 62.5 | F12: Defense T5 | G12: 150 | K12: Sessions/day (dedicated) | L12: 3
F13: Defense T6/T7 | G13: 250 | K13: Active h/day (dedicated) | L13: 2.5
A14: Rank thresholds (doc §18)
A15: Title | B15: Score | C15: Doc day target
A16: Associate | B16: 500 | C16: 2 | F16: Fees & failure economics (doc §11, §17) | K16: Population mix (Game_Economy)
A17: Researcher | B17: 3000 | C17: 7 | F17: Bracket | G17: Fee | H17: Residue value back | I17: Net fail cost | K17: % casual | L17: 0.6
A18: Senior | B18: 12000 | C18: 17 | F18: T1+T1 / T1+T2 | G18: 25 | H18: 15 | I18: =G18-H18 -> 10 | K18: % dedicated | L18: 0.3
A19: Principal | B19: 40000 | C19: 30 | F19: T2+T2 / T2+T3 | G19: 75 | H19: 30 | I19: =G19-H19 -> 45 | K19: % endgame | L19: 0.1
A20: Director | B20: 120000 | C20: 58 | F20: T3+T3 / T3+T4 | G20: 75 | H20: 60 | I20: =G20-H20 -> 15 | K20: Casual faucet/day | L20: 4000
A21: Chief Scientist | B21: 250000 | C21: 88 | F21: T4+ (Lab) | G21: 200 | H21: 90 | I21: =G21-H21 -> 110 | K21: Dedicated faucet/day | L21: 35000
F22: Joint declaration | G22: 500 | H22: 90 | I22: =G22-H22 -> 410 | K22: Endgame faucet/day | L22: 220000
K23: Casual fee sink/day | L23: 100
A24: Prestige (doc §22 v4.3): cost = ADOPTED doc value; superseded v4.2 cost kept for reference | K24: Dedicated fee sink/day | L24: 1200
A25: Level | B25: Doc cost (v4.3) | C25: Rank-gate days (model) | D25: Late-run income/day | E25: Superseded v4.2 cost | K25: Endgame fee sink/day | L25: 6000
A26: P1 | B26: 500000 | C26: 85 | D26: 60000 | E26: 500000 | K26: Share of pop in prestige cycle | L26: 0.3
A27: P2 | B27: 1500000 | C27: 72 | D27: 90000 | E27: 1500000 | K27: Avg prestige cost (active cyclers) | L27: 6000000
A28: P3 | B28: 4000000 | C28: 68 | D28: 130000 | E28: 4000000 | K28: Avg days/prestige cycle | L28: 70
A29: P4 | B29: 10000000 | C29: 62 | D29: 200000 | E29: 10000000 | K29: Players per syndicate | L29: 8
A30: P5 | B30: 25000000 | C30: 58 | D30: 300000 | E30: 25000000 | K30: Syndicates buying upgrades /mo | L30: 0.03
A31: P6 | B31: 45000000 | C31: 54 | D31: 420000 | E31: 50000000 | K31: Avg vault upgrade cost | L31: 11500000
A32: P7 | B32: 60000000 | C32: 52 | D32: 550000 | E32: 80000000
A33: P8 | B33: 75000000 | C33: 50 | D33: 650000 | E33: 128000000
A34: P9 | B34: 93750000 | C34: 49 | D34: 720000 | E34: 204800000
A35: P10 | B35: 117187500 | C35: 48 | D35: 790000 | E35: 327680000

Sheet Tiers
A1: TIER REFERENCE (doc §5, §10, §15) — values are doc constants (blue); derived columns are formulas
A3: Tier | B3: Count | C3: Run time h (online) | D3: Run time h (offline) | E3: Base value min | F3: Base value max | G3: Mid value | H3: Passive P/min | I3: Rank/run | J3: Pts/slot-h (offline) | K3: Dividend/wk | L3: Claim bonus | M3: Pts/slot-h (ONLINE — ties to doc §18)
A4: T1 | B4: 30 | C4: 0.033333333 | D4: =C4*Params!$L$10 -> 0.041666667 | E4: 10 | F4: 25 | G4: =(E4+F4)/2 -> 17.5 | H4: 8 | I4: 0 | J4: =IF(D4=0,0,I4/D4) -> 0 | K4: 0 | L4: 0 | M4: =IF(C4=0,0,I4/C4) -> 0
A5: T2 | B5: 30 | C5: 0.2 | D5: =C5*Params!$L$10 -> 0.25 | E5: 80 | F5: 150 | G5: =(E5+F5)/2 -> 115 | H5: 11.2 | I5: 3 | J5: =IF(D5=0,0,I5/D5) -> 12 | K5: 800 | L5: 1150 | M5: =IF(C5=0,0,I5/C5) -> 15
A6: T3 | B6: 30 | C6: 0.75 | D6: =C6*Params!$L$10 -> 0.9375 | E6: 400 | F6: 700 | G6: =(E6+F6)/2 -> 550 | H6: 15.7 | I6: 16 | J6: =IF(D6=0,0,I6/D6) -> 17.066667 | K6: 5000 | L6: 5500 | M6: =IF(C6=0,0,I6/C6) -> 21.333333
A7: T4 | B7: 25 | C7: 3 | D7: =C7*Params!$L$10 -> 3.75 | E7: 2000 | F7: 4000 | G7: =(E7+F7)/2 -> 3000 | H7: 21.9 | I7: 85 | J7: =IF(D7=0,0,I7/D7) -> 22.666667 | K7: 15000 | L7: 30000 | M7: =IF(C7=0,0,I7/C7) -> 28.333333
A8: T5 | B8: 20 | C8: 8 | D8: =C8*Params!$L$10 -> 10 | E8: 12000 | F8: 20000 | G8: =(E8+F8)/2 -> 16000 | H8: 30.7 | I8: 300 | J8: =IF(D8=0,0,I8/D8) -> 30 | K8: 60000 | L8: 160000 | M8: =IF(C8=0,0,I8/C8) -> 37.5
A9: T6 | B9: 15 | C9: 24 | D9: =C9 -> 24 | E9: 60000 | F9: 100000 | G9: =(E9+F9)/2 -> 80000 | H9: 43 | I9: 1150 | J9: =IF(D9=0,0,I9/D9) -> 47.916667 | K9: 100000 | L9: 800000 | M9: =IF(C9=0,0,I9/C9) -> 47.916667
A10: T7 Exotic | B10: 120 | C10: 24 | D10: =C10 -> 24 | E10: 250000 | F10: 800000 | G10: =(E10+F10)/2 -> 525000 | H10: 60 | I10: 1500 | J10: =IF(D10=0,0,I10/D10) -> 62.5 | K10: 200000 | L10: 1575000 | M10: =IF(C10=0,0,I10/C10) -> 62.5
A12: T7 claim bonus shown at 3x mid initial value (3x525,000); actual = 3x that Exotic's initial value, up to 2.4M.
A13: T1 dividend/claim are 0: patents are T2+ only (doc §15, D1). Column J = offline pace (conservative); column M = online pace and ties to doc §18 exactly (15/21.3/28.3/37.5/47.9/62.5). T6/T7 exempt from online bonus so J=M there.
A14: =IF(AND(J5<J6,J6<J7,J7<J8,J8<J9,J9<J10),"MONOTONIC (offline): PASS","MONOTONIC (offline): FAIL") -> MONOTONIC (offline): PASS
A15: =IF(AND(M5<M6,M6<M7,M7<M8,M8<=M9,M9<M10),"MONOTONIC (online): PASS","MONOTONIC (online): FAIL") -> MONOTONIC (online): PASS

Sheet Rank_Model
A1: RANK PROGRESSION MODEL — dedicated player, session-based, input-chain constrained
A2: Era completions/day are blue inputs (derived from 3-login schedule + chain math; see README). Daily rank = SUMPRODUCT vs Params rank values.
A4: Era | B4: Start day | C4: T2/d | D4: T3/d | E4: T4/d | F4: T5/d | G4: T6/d (joint) | H4: T7/d | I4: Contracts | J4: Market | K4: Defense | L4: Daily rank | N4: Sensitivity multiplier (1.0 = blended; 0.78 purist; 1.18 optimizer):
A5: T2 era | B5: 1 | C5: 28 | D5: 0 | E5: 0 | F5: 0 | G5: 0 | H5: 0 | I5: 150 | J5: 0 | K5: 0 | L5: =C5*Params!$B$7+D5*Params!$B$8+E5*Params!$B$9+F5*Params!$B$10+G5*Params!$B$11+H5*Params!$B$12+I5+J5+K5 -> 234 | N5: 1
A6: T3 era | B6: 4 | C6: 37 | D6: 18 | E6: 0 | F6: 0 | G6: 0 | H6: 0 | I6: 300 | J6: 50 | K6: 0 | L6: =C6*Params!$B$7+D6*Params!$B$8+E6*Params!$B$9+F6*Params!$B$10+G6*Params!$B$11+H6*Params!$B$12+I6+J6+K6 -> 749
A7: T4 era | B7: 11 | C7: 17 | D7: 16.5 | E7: 8.5 | F7: 0 | G7: 0 | H7: 0 | I7: 350 | J7: 100 | K7: 0 | L7: =C7*Params!$B$7+D7*Params!$B$8+E7*Params!$B$9+F7*Params!$B$10+G7*Params!$B$11+H7*Params!$B$12+I7+J7+K7 -> 1487.5
A8: T5/joint era | B8: 31 | C8: 0 | D8: 10 | E8: 5 | F8: 7 | G8: 0.4 | H8: 0 | I8: 350 | J8: 300 | K8: 25 | L8: =C8*Params!$B$7+D8*Params!$B$8+E8*Params!$B$9+F8*Params!$B$10+G8*Params!$B$11+H8*Params!$B$12+I8+J8+K8 -> 3820
A9: T6/T7 era | B9: 61 | C9: 0 | D9: 0 | E9: 4 | F9: 7 | G9: 0.6 | H9: 0.15 | I9: 350 | J9: 400 | K9: 60 | L9: =C9*Params!$B$7+D9*Params!$B$8+E9*Params!$B$9+F9*Params!$B$10+G9*Params!$B$11+H9*Params!$B$12+I9+J9+K9 -> 4165
A12: 120-DAY GRID
A13: Day | B13: Daily rank | C13: Cumulative | E13: THRESHOLD CROSSINGS
A14: 1 | B14: =VLOOKUP(A14,$B$5:$L$9,11,TRUE())*$N$5 -> 234 | C14: =B14 -> 234 | E14: Title | F14: Score | G14: Model day | H14: Doc target | I14: Delta | J14: Verdict
A15: 2 | B15: =VLOOKUP(A15,$B$5:$L$9,11,TRUE())*$N$5 -> 234 | C15: =C14+B15 -> 468 | E15: =Params!A16 -> Associate | F15: =Params!B16 -> 500 | G15: =IF(C$133>=F15,IFERROR(MATCH(F15,$C$14:$C$133)+1,1),"not by d120") -> 3 | H15: =Params!C16 -> 2 | I15: =IF(ISNUMBER(G15),G15-H15,"") -> 1 | J15: =IF(ISNUMBER(G15),IF(ABS(I15)<=H15*0.2+2,"PASS","REVIEW"),"REVIEW") -> PASS
A16: 3 | B16: =VLOOKUP(A16,$B$5:$L$9,11,TRUE())*$N$5 -> 234 | C16: =C15+B16 -> 702 | E16: =Params!A17 -> Researcher | F16: =Params!B17 -> 3000 | G16: =IF(C$133>=F16,IFERROR(MATCH(F16,$C$14:$C$133)+1,1),"not by d120") -> 7 | H16: =Params!C17 -> 7 | I16: =IF(ISNUMBER(G16),G16-H16,"") -> 0 | J16: =IF(ISNUMBER(G16),IF(ABS(I16)<=H16*0.2+2,"PASS","REVIEW"),"REVIEW") -> PASS
A17: 4 | B17: =VLOOKUP(A17,$B$5:$L$9,11,TRUE())*$N$5 -> 749 | C17: =C16+B17 -> 1451 | E17: =Params!A18 -> Senior | F17: =Params!B18 -> 12000 | G17: =IF(C$133>=F17,IFERROR(MATCH(F17,$C$14:$C$133)+1,1),"not by d120") -> 15 | H17: =Params!C18 -> 17 | I17: =IF(ISNUMBER(G17),G17-H17,"") -> -2 | J17: =IF(ISNUMBER(G17),IF(ABS(I17)<=H17*0.2+2,"PASS","REVIEW"),"REVIEW") -> PASS
A18: 5 | B18: =VLOOKUP(A18,$B$5:$L$9,11,TRUE())*$N$5 -> 749 | C18: =C17+B18 -> 2200 | E18: =Params!A19 -> Principal | F18: =Params!B19 -> 40000 | G18: =IF(C$133>=F18,IFERROR(MATCH(F18,$C$14:$C$133)+1,1),"not by d120") -> 32 | H18: =Params!C19 -> 30 | I18: =IF(ISNUMBER(G18),G18-H18,"") -> 2 | J18: =IF(ISNUMBER(G18),IF(ABS(I18)<=H18*0.2+2,"PASS","REVIEW"),"REVIEW") -> PASS
A19: 6 | B19: =VLOOKUP(A19,$B$5:$L$9,11,TRUE())*$N$5 -> 749 | C19: =C18+B19 -> 2949 | E19: =Params!A20 -> Director | F19: =Params!B20 -> 120000 | G19: =IF(C$133>=F19,IFERROR(MATCH(F19,$C$14:$C$133)+1,1),"not by d120") -> 53 | H19: =Params!C20 -> 58 | I19: =IF(ISNUMBER(G19),G19-H19,"") -> -5 | J19: =IF(ISNUMBER(G19),IF(ABS(I19)<=H19*0.2+2,"PASS","REVIEW"),"REVIEW") -> PASS
A20: 7 | B20: =VLOOKUP(A20,$B$5:$L$9,11,TRUE())*$N$5 -> 749 | C20: =C19+B20 -> 3698 | E20: =Params!A21 -> Chief Scientist | F20: =Params!B21 -> 250000 | G20: =IF(C$133>=F20,IFERROR(MATCH(F20,$C$14:$C$133)+1,1),"not by d120") -> 84 | H20: =Params!C21 -> 88 | I20: =IF(ISNUMBER(G20),G20-H20,"") -> -4 | J20: =IF(ISNUMBER(G20),IF(ABS(I20)<=H20*0.2+2,"PASS","REVIEW"),"REVIEW") -> PASS
A21: 8 | B21: =VLOOKUP(A21,$B$5:$L$9,11,TRUE())*$N$5 -> 749 | C21: =C20+B21 -> 4447
A22: 9 | B22: =VLOOKUP(A22,$B$5:$L$9,11,TRUE())*$N$5 -> 749 | C22: =C21+B22 -> 5196 | E22: Chief target band: day 85-90 (doc §18). PASS = model day within ±20% of doc target.
A23: 10 | B23: =VLOOKUP(A23,$B$5:$L$9,11,TRUE())*$N$5 -> 749 | C23: =C22+B23 -> 5945
A24: 11 | B24: =VLOOKUP(A24,$B$5:$L$9,11,TRUE())*$N$5 -> 1487.5 | C24: =C23+B24 -> 7432.5
A25: 12 | B25: =VLOOKUP(A25,$B$5:$L$9,11,TRUE())*$N$5 -> 1487.5 | C25: =C24+B25 -> 8920
A26: 13 | B26: =VLOOKUP(A26,$B$5:$L$9,11,TRUE())*$N$5 -> 1487.5 | C26: =C25+B26 -> 10407.5
A27: 14 | B27: =VLOOKUP(A27,$B$5:$L$9,11,TRUE())*$N$5 -> 1487.5 | C27: =C26+B27 -> 11895
A28: 15 | B28: =VLOOKUP(A28,$B$5:$L$9,11,TRUE())*$N$5 -> 1487.5 | C28: =C27+B28 -> 13382.5
A29: 16 | B29: =VLOOKUP(A29,$B$5:$L$9,11,TRUE())*$N$5 -> 1487.5 | C29: =C28+B29 -> 14870
A30: 17 | B30: =VLOOKUP(A30,$B$5:$L$9,11,TRUE())*$N$5 -> 1487.5 | C30: =C29+B30 -> 16357.5
A31: 18 | B31: =VLOOKUP(A31,$B$5:$L$9,11,TRUE())*$N$5 -> 1487.5 | C31: =C30+B31 -> 17845
A32: 19 | B32: =VLOOKUP(A32,$B$5:$L$9,11,TRUE())*$N$5 -> 1487.5 | C32: =C31+B32 -> 19332.5
A33: 20 | B33: =VLOOKUP(A33,$B$5:$L$9,11,TRUE())*$N$5 -> 1487.5 | C33: =C32+B33 -> 20820
A34: 21 | B34: =VLOOKUP(A34,$B$5:$L$9,11,TRUE())*$N$5 -> 1487.5 | C34: =C33+B34 -> 22307.5
... A133: 120 | B133: =VLOOKUP(A133,$B$5:$L$9,11,TRUE())*$N$5 -> 4165 | C133: =C132+B133 -> 400195

Sheet Prestige_Pacing
A1: PRESTIGE PACING — v4.3 ADOPTED costs (doc §22). Each run self-funds (Pellets reset to 500). Commitment: median dedicated run ≤ 120 days.
A3: Level | B3: Doc cost (v4.3) | C3: Rank-gate days | D3: Income/day (late-run proxy) | E3: Pellet-earn days | F3: Binding gate | G3: Run length (days) | H3: ≤120? | I3: Superseded v4.2 cost | J3: Run @ v4.2 cost | K3: ≤120 @ v4.2?
A4: =Params!A26 -> P1 | B4: =Params!B26 -> 500000 | C4: =Params!C26 -> 85 | D4: =Params!D26 -> 60000 | E4: =B4/D4 -> 8.3333333 | F4: =IF(C4>=E4,"RANK","PELLETS") -> RANK | G4: =MAX(C4,E4) -> 85 | H4: =IF(G4<=120,"OK","EXCEEDS") -> OK | I4: =Params!E26 -> 500000 | J4: =MAX(C4,I4/D4) -> 85 | K4: =IF(J4<=120,"OK","EXCEEDS") -> OK
A5: =Params!A27 -> P2 | B5: =Params!B27 -> 1500000 | C5: =Params!C27 -> 72 | D5: =Params!D27 -> 90000 | E5: =B5/D5 -> 16.666667 | F5: =IF(C5>=E5,"RANK","PELLETS") -> RANK | G5: =MAX(C5,E5) -> 72 | H5: =IF(G5<=120,"OK","EXCEEDS") -> OK | I5: =Params!E27 -> 1500000 | J5: =MAX(C5,I5/D5) -> 72 | K5: =IF(J5<=120,"OK","EXCEEDS") -> OK
A6: =Params!A28 -> P3 | B6: =Params!B28 -> 4000000 | C6: =Params!C28 -> 68 | D6: =Params!D28 -> 130000 | E6: =B6/D6 -> 30.769231 | F6: =IF(C6>=E6,"RANK","PELLETS") -> RANK | G6: =MAX(C6,E6) -> 68 | H6: =IF(G6<=120,"OK","EXCEEDS") -> OK | I6: =Params!E28 -> 4000000 | J6: =MAX(C6,I6/D6) -> 68 | K6: =IF(J6<=120,"OK","EXCEEDS") -> OK
A7: =Params!A29 -> P4 | B7: =Params!B29 -> 10000000 | C7: =Params!C29 -> 62 | D7: =Params!D29 -> 200000 | E7: =B7/D7 -> 50 | F7: =IF(C7>=E7,"RANK","PELLETS") -> RANK | G7: =MAX(C7,E7) -> 62 | H7: =IF(G7<=120,"OK","EXCEEDS") -> OK | I7: =Params!E29 -> 10000000 | J7: =MAX(C7,I7/D7) -> 62 | K7: =IF(J7<=120,"OK","EXCEEDS") -> OK
A8: =Params!A30 -> P5 | B8: =Params!B30 -> 25000000 | C8: =Params!C30 -> 58 | D8: =Params!D30 -> 300000 | E8: =B8/D8 -> 83.333333 | F8: =IF(C8>=E8,"RANK","PELLETS") -> PELLETS | G8: =MAX(C8,E8) -> 83.333333 | H8: =IF(G8<=120,"OK","EXCEEDS") -> OK | I8: =Params!E30 -> 25000000 | J8: =MAX(C8,I8/D8) -> 83.333333 | K8: =IF(J8<=120,"OK","EXCEEDS") -> OK
A9: =Params!A31 -> P6 | B9: =Params!B31 -> 45000000 | C9: =Params!C31 -> 54 | D9: =Params!D31 -> 420000 | E9: =B9/D9 -> 107.14286 | F9: =IF(C9>=E9,"RANK","PELLETS") -> PELLETS | G9: =MAX(C9,E9) -> 107.14286 | H9: =IF(G9<=120,"OK","EXCEEDS") -> OK | I9: =Params!E31 -> 50000000 | J9: =MAX(C9,I9/D9) -> 119.04762 | K9: =IF(J9<=120,"OK","EXCEEDS") -> OK
A10: =Params!A32 -> P7 | B10: =Params!B32 -> 60000000 | C10: =Params!C32 -> 52 | D10: =Params!D32 -> 550000 | E10: =B10/D10 -> 109.09091 | F10: =IF(C10>=E10,"RANK","PELLETS") -> PELLETS | G10: =MAX(C10,E10) -> 109.09091 | H10: =IF(G10<=120,"OK","EXCEEDS") -> OK | I10: =Params!E32 -> 80000000 | J10: =MAX(C10,I10/D10) -> 145.45455 | K10: =IF(J10<=120,"OK","EXCEEDS") -> EXCEEDS
A11: =Params!A33 -> P8 | B11: =Params!B33 -> 75000000 | C11: =Params!C33 -> 50 | D11: =Params!D33 -> 650000 | E11: =B11/D11 -> 115.38462 | F11: =IF(C11>=E11,"RANK","PELLETS") -> PELLETS | G11: =MAX(C11,E11) -> 115.38462 | H11: =IF(G11<=120,"OK","EXCEEDS") -> OK | I11: =Params!E33 -> 128000000 | J11: =MAX(C11,I11/D11) -> 196.92308 | K11: =IF(J11<=120,"OK","EXCEEDS") -> EXCEEDS
A12: =Params!A34 -> P9 | B12: =Params!B34 -> 93750000 | C12: =Params!C34 -> 49 | D12: =Params!D34 -> 720000 | E12: =B12/D12 -> 130.20833 | F12: =IF(C12>=E12,"RANK","PELLETS") -> PELLETS | G12: =MAX(C12,E12) -> 130.20833 | H12: =IF(G12<=120,"OK","EXCEEDS") -> EXCEEDS | I12: =Params!E34 -> 204800000 | J12: =MAX(C12,I12/D12) -> 284.44444 | K12: =IF(J12<=120,"OK","EXCEEDS") -> EXCEEDS
A13: =Params!A35 -> P10 | B13: =Params!B35 -> 117187500 | C13: =Params!C35 -> 48 | D13: =Params!D35 -> 790000 | E13: =B13/D13 -> 148.33861 | F13: =IF(C13>=E13,"RANK","PELLETS") -> PELLETS | G13: =MAX(C13,E13) -> 148.33861 | H13: =IF(G13<=120,"OK","EXCEEDS") -> EXCEEDS | I13: =Params!E35 -> 327680000 | J13: =MAX(C13,I13/D13) -> 414.78481 | K13: =IF(J13<=120,"OK","EXCEEDS") -> EXCEEDS
A15: RESOLVED IN DOC v4.3 (Section 31, D21): P6 45M, P7 60M, P8+ x1.25 adopted. P1-P8 now project <=120d (P6 ~107, P7 ~109, P8 ~115).
A16: P9/P10 (~130/148d) intentionally ride the telemetry patch lever (doc §22) — endgame income is the least certain input and the P9+ population is tiny.
A17: Columns I-K show the superseded v4.2 costs for reference: P7 ~145d, P8 ~197d — the finding that drove the recalibration.
A18: RAMP BIAS: every run restarts at 500 Pellets and re-ramps through the eras, so flat late-run income overstates earning by ~10-15% for
A19: pellet-bound levels. This makes P6-P8 WORSE than shown (P6 ~119d shown is realistically ~130d) — it strengthens, not weakens, the recommendation.

Sheet Player_Economy
A1: PER-PLAYER DAILY PELLET FLOW — by era (dedicated archetype)
A3: Era | B3: Passive income/day | C3: Compound sales/day | D3: Contracts | E3: Streak | F3: Dividends/day | G3: Total faucet/day | H3: Fees+spend/day | I3: Net savings/day
A4: T2 era (d1-3) | B4: 3500 | C4: 1500 | D4: 900 | E4: 150 | F4: 0 | G4: =SUM(B4:F4) -> 6050 | H4: 600 | I4: =G4-H4 -> 5450
A5: T3 era (d4-10) | B5: 8000 | C5: 6000 | D5: 1700 | E5: 200 | F5: 300 | G5: =SUM(B5:F5) -> 16200 | H5: 900 | I5: =G5-H5 -> 15300
A6: T4 era (d11-30) | B6: 14500 | C6: 18000 | D6: 2400 | E6: 250 | F6: 2500 | G6: =SUM(B6:F6) -> 37650 | H6: 1800 | I6: =G6-H6 -> 35850
A7: T5/joint (d31-60) | B7: 25000 | C7: 90000 | D7: 2400 | E7: 300 | F7: 12000 | G7: =SUM(B7:F7) -> 129700 | H7: 22000 | I7: =G7-H7 -> 107700
A8: T6/T7 (d61-90) | B8: 33000 | C8: 150000 | D8: 2400 | E8: 300 | F8: 20000 | G8: =SUM(B8:F8) -> 205700 | H8: 28000 | I8: =G8-H8 -> 177700
A10: Cumulative earned by day 90 (era lengths 3/7/20/30/30): | B10: =G4*3+G5*7+G6*20+G7*30+G8*30 -> 10946550
A11: P1 cost (500k) vs cumulative: rank gate binds, not Pellets — consistent with doc §22.
A13: Passive income assumptions: slots running ~60-80% of counted hours (online + offline-capped 12h); sales = production not consumed by chains, sold at mid value (Instant Sell or market net of 5%).

Sheet Game_Economy
A1: GAME-WIDE FAUCET/SINK — DAU scenarios (population mix and per-archetype rates from Params)
A3: DAU | B3: Faucets/day | C3: Fee sinks/day | D3: Prestige sink/day | E3: Vault sink/day | F3: Total sinks/day | G3: Net surplus/day | H3: Surplus/player/day
A4: 1000 | B4: =A4*(Params!$L$17*Params!$L$20+Params!$L$18*Params!$L$21+Params!$L$19*Params!$L$22) -> 34900000 | C4: =A4*(Params!$L$17*Params!$L$23+Params!$L$18*Params!$L$24+Params!$L$19*Params!$L$25) -> 1020000 | D4: =A4*Params!$L$26*Params!$L$27/Params!$L$28 -> 25714286 | E4: =A4/Params!$L$29*Params!$L$30*Params!$L$31/30 -> 1437500 | F4: =SUM(C4:E4) -> 28171786 | G4: =B4-F4 -> 6728214.3 | H4: =G4/A4 -> 6728.2143
A5: 10000 | B5: =A5*(Params!$L$17*Params!$L$20+Params!$L$18*Params!$L$21+Params!$L$19*Params!$L$22) -> 349000000 | C5: =A5*(Params!$L$17*Params!$L$23+Params!$L$18*Params!$L$24+Params!$L$19*Params!$L$25) -> 10200000 | D5: =A5*Params!$L$26*Params!$L$27/Params!$L$28 -> 2.5714286e+08 | E5: =A5/Params!$L$29*Params!$L$30*Params!$L$31/30 -> 14375000 | F5: =SUM(C5:E5) -> 2.8171786e+08 | G5: =B5-F5 -> 67282143 | H5: =G5/A5 -> 6728.2143
A6: 100000 | B6: =A6*(Params!$L$17*Params!$L$20+Params!$L$18*Params!$L$21+Params!$L$19*Params!$L$22) -> 3490000000 | C6: =A6*(Params!$L$17*Params!$L$23+Params!$L$18*Params!$L$24+Params!$L$19*Params!$L$25) -> 102000000 | D6: =A6*Params!$L$26*Params!$L$27/Params!$L$28 -> 2.5714286e+09 | E6: =A6/Params!$L$29*Params!$L$30*Params!$L$31/30 -> 143750000 | F6: =SUM(C6:E6) -> 2.8171786e+09 | G6: =B6-F6 -> 6.7282143e+08 | H6: =G6/A6 -> 6728.2143
A9: HONEST CONCLUSION: the economy runs a structural surplus (idle-genre by design). Prestige is the only sink at the right order of magnitude;
A10: fees are rounding errors. This is functional because (1) market prices are hard-bounded at 80-500% of base, (2) Prestige absorbs the wealth of
A11: exactly the players who accumulate it, (3) per-player surplus funds Prestige cycling. Doc §30's 'sinks absorb faucets' wording should later be
A12: amended to: 'Prestige absorbs per-player surplus within tolerance.' Vault sink assumes 1 syndicate per 8 players, 3%/mo buying 11.5M avg upgrades.

Sheet Discovery_Costs
A1: BRUTE-FORCE DISCOVERY COST — full map per result bracket (net of residue recovery; success fees included)
A3: Bracket | B3: Pair space | C3: Valid recipes | D3: Net fail cost | E3: Fee (success) | F3: Full-map cost | G3: Era faucet/day (links Player_Economy) | H3: Days of income
A4: T1/T2 results (T1+T1) | B4: 435 | C4: 65 | D4: =Params!$I$18 -> 10 | E4: =Params!$G$18 -> 25 | F4: =(B4-C4)*D4+C4*E4 -> 5325 | G4: =Player_Economy!G4 -> 6050 | H4: =F4/G4 -> 0.88016529
A5: T3 results (T1+T2) | B5: 900 | C5: 30 | D5: =Params!$I$18 -> 10 | E5: =Params!$G$18 -> 25 | F5: =(B5-C5)*D5+C5*E5 -> 9450 | G5: =Player_Economy!G5 -> 16200 | H5: =F5/G5 -> 0.58333333
A6: T3 results (T2+T2) | B6: 435 | C6: 20 | D6: =Params!$I$19 -> 45 | E6: =Params!$G$19 -> 75 | F6: =(B6-C6)*D6+C6*E6 -> 20175 | G6: =Player_Economy!G5 -> 16200 | H6: =F6/G6 -> 1.2453704
A7: T4 results (T2+T3) | B7: 900 | C7: 27 | D7: =Params!$I$19 -> 45 | E7: =Params!$G$19 -> 75 | F7: =(B7-C7)*D7+C7*E7 -> 41310 | G7: =Player_Economy!G6 -> 37650 | H7: =F7/G7 -> 1.0972112
A8: T4 results (T3+T3) | B8: 435 | C8: 18 | D8: =Params!$I$20 -> 15 | E8: =Params!$G$20 -> 75 | F8: =(B8-C8)*D8+C8*E8 -> 7605 | G8: =Player_Economy!G6 -> 37650 | H8: =F8/G8 -> 0.20199203
A9: T5 results (T3+T4) | B9: 750 | C9: 30 | D9: =Params!$I$20 -> 15 | E9: =Params!$G$20 -> 75 | F9: =(B9-C9)*D9+C9*E9 -> 13050 | G9: =Player_Economy!G6 -> 37650 | H9: =F9/G9 -> 0.34661355
A10: T6 joint declarations | B10: 710 | C10: 15 | D10: =Params!$I$22 -> 410 | E10: =Params!$G$22 -> 500 | F10: =(B10-C10)*D10+C10*E10 -> 292450 | G10: =Player_Economy!G7 -> 129700 | H10: =F10/G10 -> 2.2548188
A12: TOTAL (entire game): | F12: =SUM(F4:F10) -> 389365
A13: VERDICT: every bracket maps in ~0.3-2.5 days of its era's total faucet. Fees pace the first week only — discovery was never the gate (doc §11, §17). T3 cheapness validated as intended. Valid-recipe splits per bracket (col C) are assumptions; totals tie to doc §7 (~205 recipes).
A15: DISCLOSURE: the 'Valid recipes' column counts result MAPPINGS (matching doc §7 and the compound database's density). Valid PAIRS are slightly fewer where pairs are variable (e.g. 28 pairs carry the 30 T1+T2->T3 mappings); discovery pays one fee per PAIR, so full-map costs above are overstated by ~0.3%. Immaterial; per-pair data lives in PRECIPICE_COMPOUND_DATABASE.xlsx.

Sheet Exotic_Decay
A1: EXOTIC VALUE DECAY — value = initial x MAX(decay^units, floor) (doc §23)
A2: Initial value (mid): | B2: 525000
A4: Run # | B4: Units created (cum) | C4: Value multiplier | D4: Current value | E4: Revenue this run (2 units) | F4: Cumulative revenue | H4: Floor reached at unit:
A5: 0 | B5: =A5*2 -> 0 | C5: =MAX(Params!$L$5^B5,Params!$L$6) -> 1 | D5: =$B$2*C5 -> 525000 | E5: =IF(A5=0,0,2*$B$2*MAX(Params!$L$5^B5,Params!$L$6)) -> 0 | F5: =E5 -> 0 | H5: =MATCH(TRUE(),INDEX($C$5:$C$35=Params!$L$6,0),0)*2-2 -> 46
A6: 1 | B6: =A6*2 -> 2 | C6: =MAX(Params!$L$5^B6,Params!$L$6) -> 0.9409 | D6: =$B$2*C6 -> 493972.5 | E6: =IF(A6=0,0,2*$B$2*MAX(Params!$L$5^B6,Params!$L$6)) -> 987945 | F6: =F5+E6 -> 987945 | H6: Doc claim: ~unit 46-48 / run 24. Verify left.
A7: 2 | B7: =A7*2 -> 4 | C7: =MAX(Params!$L$5^B7,Params!$L$6) -> 0.88529281 | D7: =$B$2*C7 -> 464778.73 | E7: =IF(A7=0,0,2*$B$2*MAX(Params!$L$5^B7,Params!$L$6)) -> 929557.45 | F7: =F6+E7 -> 1917502.5
A8: 3 | B8: =A8*2 -> 6 | C8: =MAX(Params!$L$5^B8,Params!$L$6) -> 0.832972 | D8: =$B$2*C8 -> 437310.3 | E8: =IF(A8=0,0,2*$B$2*MAX(Params!$L$5^B8,Params!$L$6)) -> 874620.61 | F8: =F7+E8 -> 2792123.1 | H8: Claim bonus (3x initial) and 200k/wk dividend are decay-immune (doc §23).
A9: 4 | B9: =A9*2 -> 8 | C9: =MAX(Params!$L$5^B9,Params!$L$6) -> 0.78374336 | D9: =$B$2*C9 -> 411465.26 | E9: =IF(A9=0,0,2*$B$2*MAX(Params!$L$5^B9,Params!$L$6)) -> 822930.53 | F9: =F8+E9 -> 3615053.6 | H9: Revenue prices both units at the post-run global count (doc §23: value = initial x decay^(total units ever created)).
A10: 5 | B10: =A10*2 -> 10 | C10: =MAX(Params!$L$5^B10,Params!$L$6) -> 0.73742413 | D10: =$B$2*C10 -> 387147.67 | E10: =IF(A10=0,0,2*$B$2*MAX(Params!$L$5^B10,Params!$L$6)) -> 774295.33 | F10: =F9+E10 -> 4389348.9
A11: 6 | B11: =A11*2 -> 12 | C11: =MAX(Params!$L$5^B11,Params!$L$6) -> 0.69384236 | D11: =$B$2*C11 -> 364267.24 | E11: =IF(A11=0,0,2*$B$2*MAX(Params!$L$5^B11,Params!$L$6)) -> 728534.48 | F11: =F10+E11 -> 5117883.4
A12: 7 | B12: =A12*2 -> 14 | C12: =MAX(Params!$L$5^B12,Params!$L$6) -> 0.65283628 | D12: =$B$2*C12 -> 342739.05 | E12: =IF(A12=0,0,2*$B$2*MAX(Params!$L$5^B12,Params!$L$6)) -> 685478.09 | F12: =F11+E12 -> 5803361.5
A13: 8 | B13: =A13*2 -> 16 | C13: =MAX(Params!$L$5^B13,Params!$L$6) -> 0.61425365 | D13: =$B$2*C13 -> 322483.17 | E13: =IF(A13=0,0,2*$B$2*MAX(Params!$L$5^B13,Params!$L$6)) -> 644966.34 | F13: =F12+E13 -> 6448327.8
A14: 9 | B14: =A14*2 -> 18 | C14: =MAX(Params!$L$5^B14,Params!$L$6) -> 0.57795126 | D14: =$B$2*C14 -> 303424.41 | E14: =IF(A14=0,0,2*$B$2*MAX(Params!$L$5^B14,Params!$L$6)) -> 606848.83 | F14: =F13+E14 -> 7055176.6
A15: 10 | B15: =A15*2 -> 20 | C15: =MAX(Params!$L$5^B15,Params!$L$6) -> 0.54379434 | D15: =$B$2*C15 -> 285492.03 | E15: =IF(A15=0,0,2*$B$2*MAX(Params!$L$5^B15,Params!$L$6)) -> 570984.06 | F15: =F14+E15 -> 7626160.7
A16: 11 | B16: =A16*2 -> 22 | C16: =MAX(Params!$L$5^B16,Params!$L$6) -> 0.5116561 | D16: =$B$2*C16 -> 268619.45 | E16: =IF(A16=0,0,2*$B$2*MAX(Params!$L$5^B16,Params!$L$6)) -> 537238.9 | F16: =F15+E16 -> 8163399.6
A17: 12 | B17: =A17*2 -> 24 | C17: =MAX(Params!$L$5^B17,Params!$L$6) -> 0.48141722 | D17: =$B$2*C17 -> 252744.04 | E17: =IF(A17=0,0,2*$B$2*MAX(Params!$L$5^B17,Params!$L$6)) -> 505488.08 | F17: =F16+E17 -> 8668887.7
A18: 13 | B18: =A18*2 -> 26 | C18: =MAX(Params!$L$5^B18,Params!$L$6) -> 0.45296546 | D18: =$B$2*C18 -> 237806.87 | E18: =IF(A18=0,0,2*$B$2*MAX(Params!$L$5^B18,Params!$L$6)) -> 475613.74 | F18: =F17+E18 -> 9144501.4
A19: 14 | B19: =A19*2 -> 28 | C19: =MAX(Params!$L$5^B19,Params!$L$6) -> 0.42619521 | D19: =$B$2*C19 -> 223752.48 | E19: =IF(A19=0,0,2*$B$2*MAX(Params!$L$5^B19,Params!$L$6)) -> 447504.97 | F19: =F18+E19 -> 9592006.4
A20: 15 | B20: =A20*2 -> 30 | C20: =MAX(Params!$L$5^B20,Params!$L$6) -> 0.40100707 | D20: =$B$2*C20 -> 210528.71 | E20: =IF(A20=0,0,2*$B$2*MAX(Params!$L$5^B20,Params!$L$6)) -> 421057.42 | F20: =F19+E20 -> 10013064
A21: 16 | B21: =A21*2 -> 32 | C21: =MAX(Params!$L$5^B21,Params!$L$6) -> 0.37730755 | D21: =$B$2*C21 -> 198086.46 | E21: =IF(A21=0,0,2*$B$2*MAX(Params!$L$5^B21,Params!$L$6)) -> 396172.93 | F21: =F20+E21 -> 10409237
... A35: 30 | B35: =A35*2 -> 60 | C35: =MAX(Params!$L$5^B35,Params!$L$6) -> 0.25 | D35: =$B$2*C35 -> 131250 | E35: =IF(A35=0,0,2*$B$2*MAX(Params!$L$5^B35,Params!$L$6)) -> 262500 | F35: =F34+E35 -> 14440253

Sheet Patents_Defense
A1: PATENT DIVIDENDS & DEFENSE WINDOW MATH (doc §15)
A3: Tier | B3: Patent count | C3: Dividend/wk | D3: Game-wide max/wk | E3: Defense window (h) | F3: Run time offline (h) | G3: Completions/slot/window | H3: Completions/slot ONLINE max (ties doc §15 table)
A4: T2 | B4: =Tiers!B5 -> 30 | C4: =Tiers!K5 -> 800 | D4: =B4*C4 -> 24000 | E4: 72 | F4: =Tiers!D5 -> 0.25 | G4: =E4/F4 -> 288 | H4: =E4/Tiers!C5 -> 360
A5: T3 | B5: =Tiers!B6 -> 30 | C5: =Tiers!K6 -> 5000 | D5: =B5*C5 -> 150000 | E5: 72 | F5: =Tiers!D6 -> 0.9375 | G5: =E5/F5 -> 76.8 | H5: =E5/Tiers!C6 -> 96
A6: T4 | B6: =Tiers!B7 -> 25 | C6: =Tiers!K7 -> 15000 | D6: =B6*C6 -> 375000 | E6: 96 | F6: =Tiers!D7 -> 3.75 | G6: =E6/F6 -> 25.6 | H6: =E6/Tiers!C7 -> 32
A7: T5 | B7: =Tiers!B8 -> 20 | C7: =Tiers!K8 -> 60000 | D7: =B7*C7 -> 1200000 | E7: 120 | F7: =Tiers!D8 -> 10 | G7: =E7/F7 -> 12 | H7: =E7/Tiers!C8 -> 15
A8: T6 | B8: =Tiers!B9 -> 15 | C8: =Tiers!K9 -> 100000 | D8: =B8*C8 -> 1500000 | E8: 168 | F8: =Tiers!D9 -> 24 | G8: =E8/F8 -> 7 | H8: =E8/Tiers!C9 -> 7
A9: T7 Exotic | B9: =Tiers!B10 -> 120 | C9: =Tiers!K10 -> 200000 | D9: =B9*C9 -> 24000000 | E9: 168 | F9: =Tiers!D10 -> 24 | G9: =E9/F9 -> 7 | H9: =E9/Tiers!C10 -> 7
A11: Theoretical max dividends/wk — ALL patents T2-T7, one holder: | B11: T6+T7 only (doc §15 quotes 25.5M): | C11: =D8+D9 -> 25500000 | D11: =SUM(D4:D9) -> 27249000
A12: Base game T2-T6 only (doc §30 quotes ~3.25M): | D12: =SUM(D4:D8) -> 3249000
A13: VERDICT: every tier permits >=7 natural completions/slot per window — every defense is contestable. Column G = offline pace (realistic floor); column H = online max and ties to doc §15 exactly (360/96/32/15/7). T6/T7 with 2-3 joint slots: 14-21.

Sheet Event_Flux
A1: CASCADE PROTOCOL FLUX MODEL (doc §29) — Flux/run = rank value; extraction 1 Flux capped 50/day (post-multiplier)
A3: Player era | B3: Flux/day (= PRODUCTION rank only — contracts/market/defense earn no Flux) | C3: Blueprint | D3: Cost | E3: Days to afford | F3: Days w/ event pass (2x)
A4: New player (extraction cap) | B4: 50 | C4: Cascade Trace | D4: 50 | E4: =D4/B4 -> 1 | F4: =D4/(B4*2) -> 0.5
A5: T3 era | B5: =Rank_Model!C6*Params!$B$7+Rank_Model!D6*Params!$B$8+Rank_Model!E6*Params!$B$9+Rank_Model!F6*Params!$B$10+Rank_Model!G6*Params!$B$11+Rank_Model!H6*Params!$B$12 -> 399 | C5: Alpha/Beta | D5: 300 | E5: =D5/B5 -> 0.7518797 | F5: =D5/(B5*2) -> 0.37593985
A6: T4 era | B6: =Rank_Model!C7*Params!$B$7+Rank_Model!D7*Params!$B$8+Rank_Model!E7*Params!$B$9+Rank_Model!F7*Params!$B$10+Rank_Model!G7*Params!$B$11+Rank_Model!H7*Params!$B$12 -> 1037.5 | C6: Gamma/Delta | D6: 1200 | E6: =D6/B6 -> 1.1566265 | F6: =D6/(B6*2) -> 0.57831325
A7: T5 era | B7: =Rank_Model!C8*Params!$B$7+Rank_Model!D8*Params!$B$8+Rank_Model!E8*Params!$B$9+Rank_Model!F8*Params!$B$10+Rank_Model!G8*Params!$B$11+Rank_Model!H8*Params!$B$12 -> 3145 | C7: Epsilon/Omega | D7: 4000 | E7: =D7/B7 -> 1.2718601 | F7: =D7/(B7*2) -> 0.63593005
A9: VERDICT: Trace day 1 for brand-new players (doc claim holds); top blueprints ~1.3-4 days at era pace inside a 21-day event. Pass halves it. PASS.
A12: Milestone target example: | C12: DAU | D12: Avg Flux/day/player | E12: Event days | F12: Calibration
B13: =C13*D13*E13*F13 -> 113400000 | C13: 10000 | D13: 900 | E13: 21 | F13: 0.6

Sheet Tuning_Flags
A1: TUNING FLAGS — every §30-flagged parameter, validated verdict
A3: Parameter | B3: Doc value | C3: Verdict | D3: Finding / recommendation
A4: Rank production values + thresholds | B4: 0/3/16/85/300/1150/1500; Chief 250k | C4: PASS | D4: Chief lands day ~84 blended (75 optimizer / 101 purist) vs 85-90 target. All intermediate thresholds within ±3 days of doc labels. Monotonic per-slot-hour confirmed (Tiers!A14). No change.
A5: Formula Lab fees vs zero-cost failure | B5: 25/75/200; net 10/45/15/110 | C5: PASS | D5: Full-map cost per bracket = 0.3-2.5 days of era income. Discovery paces week 1 only, which is the design intent. T3 bracket cheapness intentional and harmless.
A6: Joint analysis declaration fee | B6: 500 (300 P1+) | C6: PASS | D6: Full 710-pair map ~292k net — 2.3 days of T5-era income. Paid probing as intended.
A7: Exotic decay constant + floor | B7: 0.97 / 25% | C7: PASS | D7: Floor at unit 46 (run 24) — matches doc exactly. Floored values 62.5k-200k as documented.
A8: Defense windows | B8: 72h/96h/120h/7d | C8: PASS | D8: 7 (T6/T7, per joint slot) to 288 offline / 360 online completions per slot per window — sheet now shows both paces; online column ties doc §15 exactly. Every tier contestable.
A9: Blueprint Flux prices + extraction cap | B9: 50/300/1200/4000; cap 50/day | C9: PASS | D9: Trace day 1 for new players; Epsilon ~1.3d at T5 pace. Cap post-multiplier holds.
A10: Tier-scaled defense rank | B10: 25/50/100/150/250 | C10: PASS | D10: T2 collusion ping-pong yields 25/defense vs 7-day immunity gate — worthless. T6 250 dwarfed by 1,150 production. No change.
A11: Joint passive income (both members full rate) | B11: 43-60 P/min each | C11: PASS | D11: T6 run pays ~62k passive per member per run — large but endgame-appropriate; dividends dominate anyway.
A12: Prestige costs P1-P6 | B12: 500k-50M | C12: RESOLVED v4.3 | D12: P6 cut 50M->45M in doc v4.3 (D21); P1-P5 unchanged. All P1-P6 project <=110d with ramp bias acknowledged.
A13: Prestige costs P7+ | B13: 80M, x1.6 | C13: RESOLVED v4.3 | D13: ADOPTED in doc v4.3 (Section 31, D21): P7 60M, P8+ x1.25. P7 ~109d, P8 ~115d — inside the commitment. P9+ (~130/148d) explicitly assigned to the §22 telemetry patch lever. Superseded v4.2 costs kept in Params col E / Prestige_Pacing cols I-K for reference.
A14: Faucet/sink balance (§30 wording) | B14: 'sinks absorb faucets' | C14: RESOLVED v4.3 | D14: §30 restated in doc v4.3 (D22): Prestige absorbs per-player surplus within committed pacing; Market bounds insulate prices; vault upgrades absorb Syndicate surplus; fee sinks pace behavior only. Structural surplus ~5-8k/player/day is genre-correct and now honestly framed.
... A17: Contract pool draw weights & rewards | B17: 24 templates; 3 std (E60/M40) + 2 bonus (M30/H70) | C17: AUTHORED (v4.5) | D17: Contract_Pool sheet (E9). All rewards inside doc §19 bands; expected all-five daily rank ≈390, typical band matches doc’s “roughly 250–475”. Weights tunable.

Sheet Contract_Pool
A1: CONTRACT POOL — the full authored daily-contract pool (doc §19, v4.5 ruling E9). 24 templates; rewards inside doc §19 bands (Easy 200–500/25, Medium 500–1,500/75, Hard 1,500–3,000/150).
A2: Skipped runs count toward all contracts (doc §14/§19). “Analyses” = personal Formula Lab analyses only — never joint declarations (doc D18). Filters use the “possible in principle” standard (doc D9/D20), evaluated at generation.
A3: ID | B3: Contract (target shown in name) | C3: Difficulty | D3: Target | E3: Pellet reward | F3: Rank score | G3: State filter at generation | H3: Notes
A4: CE1 | B4: Synthesize 5 Tier 2 compounds | C4: Easy | D4: 5 | E4: 400 | F4: 25 | G4: ≥1 discovered recipe producing T2 | H4: Skipped runs count
A5: CE2 | B5: Complete 2 Formula Lab analyses | C5: Easy | D5: 2 | E5: 300 | F5: 25 | G5: None (Lab always available) | H5: Personal Lab analyses only (D18)
A6: CE3 | B6: Instant-sell a compound | C6: Easy | D6: 1 | E6: 200 | F6: 25 | G6: None
A7: CE4 | B7: Synthesize 3 Tier 2 compounds | C7: Easy | D7: 3 | E7: 300 | F7: 25 | G7: ≥1 discovered recipe producing T2
A8: CE5 | B8: Complete 4 Formula Lab analyses | C8: Easy | D8: 4 | E8: 450 | F8: 25 | G8: None
A9: CE6 | B9: Instant-sell 3 compounds | C9: Easy | D9: 3 | E9: 350 | F9: 25 | G9: None
A10: CE7 | B10: List a compound on the Market | C10: Easy | D10: 1 | E10: 250 | F10: 25 | G10: None | H10: Listing fee applies normally
A11: CE8 | B11: Sell 3 Inert Residue | C11: Easy | D11: 3 | E11: 200 | F11: 25 | G11: None | H11: Residue obtainable from any failed analysis
A12: CM1 | B12: List 3 compounds on the Market | C12: Medium | D12: 3 | E12: 600 | F12: 75 | G12: None
A13: CM2 | B13: Contribute 500 Pellets to your Syndicate vault | C13: Medium | D13: 500 | E13: 500 | F13: 75 | G13: Syndicate member | H13: Counts toward the 500/day contribution rank cap normally
A14: CM3 | B14: Synthesize 5 Tier 3 compounds | C14: Medium | D14: 5 | E14: 900 | F14: 75 | G14: ≥1 discovered recipe producing T3
A15: CM4 | B15: Buy a compound from the Market | C15: Medium | D15: 1 | E15: 700 | F15: 75 | G15: None
A16: CM5 | B16: Complete 6 Formula Lab analyses | C16: Medium | D16: 6 | E16: 800 | F16: 75 | G16: None
A17: CM6 | B17: Synthesize 8 Tier 2 compounds | C17: Medium | D17: 8 | E17: 750 | F17: 75 | G17: ≥1 discovered recipe producing T2
A18: CM7 | B18: Discover a new recipe | C18: Medium | D18: 1 | E18: 1200 | F18: 75 | G18: ≥1 undiscovered pair remaining | H18: Always true in practice outside a fully mapped account
A19: CM8 | B19: Contribute 1,500 Pellets to your Syndicate vault | C19: Medium | D19: 1500 | E19: 1000 | F19: 75 | G19: Syndicate member
A20: CH1 | B20: Complete a Joint Synthesis | C20: Hard | D20: 1 | E20: 1500 | F20: 150 | G20: Syndicate member + T4 qualification | H20: Either contributor role qualifies; Accelerated runs count (contracts measure activity)
A21: CH2 | B21: Take a patent or successfully defend one of yours | C21: Hard | D21: 1 | E21: 2000 | F21: 150 | G21: ≥1 discovered T2+ recipe (D20) | H21: “Possible in principle” standard; quiet days unfinished is intended
A22: CH3 | B22: Synthesize 3 Tier 4 compounds | C22: Hard | D22: 3 | E22: 1800 | F22: 150 | G22: ≥1 discovered recipe producing T4
A23: CH4 | B23: Synthesize 2 Tier 5 compounds | C23: Hard | D23: 2 | E23: 2200 | F23: 150 | G23: ≥1 discovered recipe producing T5 + Syndicate member | H23: T5 requires membership (doc §7)
A24: CH5 | B24: Earn 5,000 Pellets from Market sales | C24: Hard | D24: 5000 | E24: 1600 | F24: 150 | G24: None | H24: Completed sales only; Instant Sell excluded
A25: CH6 | B25: Synthesize 10 Tier 3 compounds | C25: Hard | D25: 10 | E25: 1700 | F25: 150 | G25: ≥1 discovered recipe producing T3
A26: CH7 | B26: Complete 10 Formula Lab analyses | C26: Hard | D26: 10 | E26: 1500 | F26: 150 | G26: None
A27: CH8 | B27: Complete a Stabilized Synthesis | C27: Hard | D27: 1 | E27: 1900 | F27: 150 | G27: ≥1 discovered variant of a variable pair | H27: Pulls players into the weekly-seed system; Stabilized counts as natural (doc §14)
A29: DRAW RULE (v4.5 E9): 5 contracts/day per player — 3 standard slots drawn from the Easy (60%) / Medium (40%) pools, 2 bonus slots drawn from the Medium (30%) / Hard (70%) pools. No template repeats within a day. Templates whose filter fails at generation are excluded from that day’s draw.
A30: All-five daily rank bonus by mix: min = | B30: =3*25+2*75 -> 225 | C30: (3 Easy + 2 Medium)
A31: max = | B31: =3*75+2*150 -> 525 | C31: (3 Medium + 2 Hard)
A32: expected = | B32: =3*(0.6*25+0.4*75)+2*(0.3*75+0.7*150) -> 390 | C32: Typical band straddles doc §19’s “roughly 250–475”; extremes 225/525 are rare mixes.

Sheet Catalyst_Economy
A1: CATALYST ECONOMY — first model of the premium currency (doc §3, §25; v4.5 ruling E10). Blue = doc constants (tunable).
A3: FREE EARN SOURCES (doc §3)
A4: Source | B4: Catalysts | C4: Cadence | D4: Per year (steady state)
A5: Login streak day 7 / 14 / 28 (first month, one-time per streak) | B5: 8 | C5: once per unbroken first month | D5: —
A6: Login streak day 35+ steady state | B6: 1 | C6: per 7 days | D6: =B6*52 -> 52
A7: Seasonal event shared milestone | B7: 25 | C7: per event (assume 2 events/yr) | D7: =B7*2 -> 50
A8: World-first patent claim | B8: 5 | C8: once per compound ever — 240 base+Exotic firsts game-wide, finite | D8: not a steady-state source
A9: TOTAL steady state, streak-keeping non-payer, zero world firsts | D9: =D6+D7 -> 102
A10: ≈ per month | D10: =D9/12 -> 8.5
A12: PRICES (doc §3, §17, §24, §25)
A13: Item | B13: Catalyst cost | C13: Months of free earn to afford | D13: Cash-equivalent R$ (at best pack rate)
A14: Timer skip (one slot) | B14: 30 | C14: =B14/$D$10 -> 3.5294118 | D14: =B14*$B$22 -> 100
A15: Joint Synthesis −25% acceleration | B15: 30 | C15: =B15/$D$10 -> 3.5294118 | D15: =B15*$B$22 -> 100
A16: Premium cosmetics (range low) | B16: 20 | C16: =B16/$D$10 -> 2.3529412 | D16: =B16*$B$22 -> 66.666667
A17: Premium cosmetics (range high) | B17: 200 | C17: =B17/$D$10 -> 23.529412 | D17: =B17*$B$22 -> 666.66667
A18: Syndicate member-cap expansion (Founder, one-time) | B18: 200 | C18: =B18/$D$10 -> 23.529412 | D18: =B18*$B$22 -> 666.66667
A20: ROBUX CONVERSION (doc §25)
A21: CatalystS: 200 R$ → 50 Cat; R$/Cat = | B21: =200/50 -> 4
A22: CatalystL: 500 R$ → 150 Cat; R$/Cat (best rate) = | B22: =500/150 -> 3.3333333
A23: TimerSkip direct: 75 R$ vs Catalyst skip ≈ | B23: =30*B22 -> 100 | C23: R$ equivalent — direct skip is always the efficient cash path; Catalysts exist for the Catalyst-exclusive items (acceleration, expansion, cosmetics)
A25: VERDICT
A26: Free Catalysts are deliberately scarce (~8–9/month steady state incl. events): they fund roughly one skip or acceleration per month, or save toward cosmetics/expansion over months. This is correct for a premium currency whose only competitive-adjacent use (skips) is competitively worthless by the Natural Completion Rule. STANDING FLAG (§30): if telemetry shows near-zero non-payer engagement with Catalyst-priced features, the first lever is the streak steady-state rate (1 → 2 per week), never price cuts — cutting prices devalues purchased Catalysts.
