Workbook

Sheet README
A1: PRECIPICE COMPOUND DATABASE v2 — companion to PRECIPICE_GAME_DESIGN_v4.6.md and PRECIPICE_ECONOMY_MODEL.xlsx (58-point cross-verification passed at v4.4; v4.5 changed no shared numbers — its rulings are implementation-seam only (doc Part E))
A3: CONTENT: 150 base compounds, 205 recipe mappings (188 pairs, 17 variable), 120 seeded Exotics, 7 Cascade event compounds.
A5: CHEMISTRY CONVENTIONS (v2 — the element-conservation rebuild):
A6: 1. THE ELEMENT LAW: T1 extraction is the game's only element faucet. The 30 T1 compounds carry the full 29-element palette; every higher compound's key elements must flow up from T1 through its recipe chain.
A7: 2. Synthesis recipes (T2-T4, and element-keyed T5) conserve metals: a result's key elements must be present in its inputs. Anions and atmosphere — O, C, N, S, Cl, I, H, F — are facility process feeds and are free. This makes mixed-oxide routes genuinely accurate (Zinc Titanate <- a Zn source + a Ti source) and alloy/ceramic routes directionally plausible.
A8: 3. T1 discovery pairs do NOT conserve (you cannot make magnesium from sodium): per doc §6 they are analytical signatures that unlock extraction licenses, not syntheses. Shared-element pairs are preferred for flavor.
A9: 4. Variable pairs are POLYMORPH COUPLES: same reagents, two phases — both variants element-covered by the one pair. The seed picking the weekly phase is now chemically motivated fiction.
A10: 5. T5 process/structure names (Graphene Lattice, Metamaterial Substrate...) and all T6 names are frontier fiction, exempt from conservation. Cascade event compounds are event fiction, exempt. All authored recipes use two DISTINCT compounds; same-compound pairs exist only as joint declarations — always invalid at T4+T5/T5+T5 (fee, residue, no staging), always an Exotic at T6+T6 (doc §17, §23).
A12: EXOTICS: the doc (§23) says the server generates an Exotic on a pair's first completion. The Exotics sheet IS that generator's output, shipped as data — deterministic, name-collision-free, includes the doc's three example names at real slots. Server implementation is a table lookup. This is the implementation of §23, not a change to it.
A14: COLOR CODE: BLUE = authored content (edit). GREEN = formula links (never edit). Flavor text is draft copy — the only non-load-bearing column.
A15: REGENERATION: gen_compounds_v2.py, seed 92136505. Hand edits to recipe wiring are allowed but MUST re-run the structural checks — reachability and element flow cannot be eyeballed.
A16: KNOWN NUANCE: the economy model's Discovery_Costs 'valid' column counts mappings; valid PAIRS are slightly fewer where variable. Cost impact ~0.3%, immaterial, disclosed.

Sheet Tier_Constants
A1: TIER CONSTANTS (doc §5)
A2: Tier | B2: Time (min, online) | C2: Passive P/min | D2: Value min | E2: Value max
A3: 1 | B3: 2 | C3: 8 | D3: 10 | E3: 25
A4: 2 | B4: 12 | C4: 11.2 | D4: 80 | E4: 150
A5: 3 | B5: 45 | C5: 15.7 | D5: 400 | E5: 700
A6: 4 | B6: 180 | C6: 21.9 | D6: 2000 | E6: 4000
A7: 5 | B7: 480 | C7: 30.7 | D7: 12000 | E7: 20000
A8: 6 | B8: 1440 | C8: 43 | D8: 60000 | E8: 100000

Sheet Compounds
A1: COMPOUND DATABASE — 150 base compounds, element-conserving chemistry (PRECIPICE_GAME_DESIGN_v4.6 §4-§7)
A2: ID | B2: Name | C2: Tier | D2: Starter | E2: Key elements | F2: Base value | G2: Time (min) | H2: Passive P/min | I2: # recipes producing | J2: Used as input | K2: Variable variant? | L2: Flavor (draft copy)
A3: T1_01 | B3: Sodium Chloride | C3: 1 | D3: YES | E3: Na | F3: 25 | G3: =VLOOKUP(C3,Tier_Constants!$A$3:$E$8,2,FALSE()) -> 2 | H3: =VLOOKUP(C3,Tier_Constants!$A$3:$E$8,3,FALSE()) -> 8 | I3: =COUNTIF(Recipes!$B$3:$B$207,A3) -> 0 | J3: =COUNTIF(Recipes!$E$3:$E$207,A3)+COUNTIF(Recipes!$G$3:$G$207,A3) -> 7 | K3: =IF(COUNTIFS(Recipes!$B$3:$B$207,A3,Recipes!$I$3:$I$207,"<>simple")>0,"YES","") | L3: Raw feedstock pulled straight from the extraction line.
A4: T1_02 | B4: Calcium Oxide | C4: 1 | D4: YES | E4: Ca | F4: 22 | G4: =VLOOKUP(C4,Tier_Constants!$A$3:$E$8,2,FALSE()) -> 2 | H4: =VLOOKUP(C4,Tier_Constants!$A$3:$E$8,3,FALSE()) -> 8 | I4: =COUNTIF(Recipes!$B$3:$B$207,A4) -> 0 | J4: =COUNTIF(Recipes!$E$3:$E$207,A4)+COUNTIF(Recipes!$G$3:$G$207,A4) -> 6 | K4: =IF(COUNTIFS(Recipes!$B$3:$B$207,A4,Recipes!$I$3:$I$207,"<>simple")>0,"YES","") | L4: A commodity-grade base material every lab burns through daily.
A5: T1_03 | B5: Zinc Sulfate | C5: 1 | D5: YES | E5: Zn | F5: 24 | G5: =VLOOKUP(C5,Tier_Constants!$A$3:$E$8,2,FALSE()) -> 2 | H5: =VLOOKUP(C5,Tier_Constants!$A$3:$E$8,3,FALSE()) -> 8 | I5: =COUNTIF(Recipes!$B$3:$B$207,A5) -> 0 | J5: =COUNTIF(Recipes!$E$3:$E$207,A5)+COUNTIF(Recipes!$G$3:$G$207,A5) -> 5 | K5: =IF(COUNTIFS(Recipes!$B$3:$B$207,A5,Recipes!$I$3:$I$207,"<>simple")>0,"YES","") | L5: Unremarkable on its own; indispensable in everything.
A6: T1_04 | B6: Iron Acetate | C6: 1 | D6: YES | E6: Fe | F6: 12 | G6: =VLOOKUP(C6,Tier_Constants!$A$3:$E$8,2,FALSE()) -> 2 | H6: =VLOOKUP(C6,Tier_Constants!$A$3:$E$8,3,FALSE()) -> 8 | I6: =COUNTIF(Recipes!$B$3:$B$207,A6) -> 0 | J6: =COUNTIF(Recipes!$E$3:$E$207,A6)+COUNTIF(Recipes!$G$3:$G$207,A6) -> 6 | K6: =IF(COUNTIFS(Recipes!$B$3:$B$207,A6,Recipes!$I$3:$I$207,"<>simple")>0,"YES","") | L6: The first thing a new researcher learns to extract.
A7: T1_05 | B7: Potassium Iodide | C7: 1 | D7: YES | E7: K | F7: 11 | G7: =VLOOKUP(C7,Tier_Constants!$A$3:$E$8,2,FALSE()) -> 2 | H7: =VLOOKUP(C7,Tier_Constants!$A$3:$E$8,3,FALSE()) -> 8 | I7: =COUNTIF(Recipes!$B$3:$B$207,A7) -> 0 | J7: =COUNTIF(Recipes!$E$3:$E$207,A7)+COUNTIF(Recipes!$G$3:$G$207,A7) -> 5 | K7: =IF(COUNTIFS(Recipes!$B$3:$B$207,A7,Recipes!$I$3:$I$207,"<>simple")>0,"YES","") | L7: Cheap, stable, and always in demand on the floor.
A8: T1_06 | B8: Magnesium Chloride | C8: 1 | E8: Mg | F8: 14 | G8: =VLOOKUP(C8,Tier_Constants!$A$3:$E$8,2,FALSE()) -> 2 | H8: =VLOOKUP(C8,Tier_Constants!$A$3:$E$8,3,FALSE()) -> 8 | I8: =COUNTIF(Recipes!$B$3:$B$207,A8) -> 1 | J8: =COUNTIF(Recipes!$E$3:$E$207,A8)+COUNTIF(Recipes!$G$3:$G$207,A8) -> 6 | K8: =IF(COUNTIFS(Recipes!$B$3:$B$207,A8,Recipes!$I$3:$I$207,"<>simple")>0,"YES","") | L8: Raw feedstock pulled straight from the extraction line.
A9: T1_07 | B9: Copper Sulfate | C9: 1 | E9: Cu | F9: 16 | G9: =VLOOKUP(C9,Tier_Constants!$A$3:$E$8,2,FALSE()) -> 2 | H9: =VLOOKUP(C9,Tier_Constants!$A$3:$E$8,3,FALSE()) -> 8 | I9: =COUNTIF(Recipes!$B$3:$B$207,A9) -> 1 | J9: =COUNTIF(Recipes!$E$3:$E$207,A9)+COUNTIF(Recipes!$G$3:$G$207,A9) -> 6 | K9: =IF(COUNTIFS(Recipes!$B$3:$B$207,A9,Recipes!$I$3:$I$207,"<>simple")>0,"YES","") | L9: A commodity-grade base material every lab burns through daily.
A10: T1_08 | B10: Aluminum Oxide | C10: 1 | E10: Al | F10: 21 | G10: =VLOOKUP(C10,Tier_Constants!$A$3:$E$8,2,FALSE()) -> 2 | H10: =VLOOKUP(C10,Tier_Constants!$A$3:$E$8,3,FALSE()) -> 8 | I10: =COUNTIF(Recipes!$B$3:$B$207,A10) -> 1 | J10: =COUNTIF(Recipes!$E$3:$E$207,A10)+COUNTIF(Recipes!$G$3:$G$207,A10) -> 6 | K10: =IF(COUNTIFS(Recipes!$B$3:$B$207,A10,Recipes!$I$3:$I$207,"<>simple")>0,"YES","") | L10: Unremarkable on its own; indispensable in everything.
A11: T1_09 | B11: Silicon Dioxide | C11: 1 | E11: Si | F11: 24 | G11: =VLOOKUP(C11,Tier_Constants!$A$3:$E$8,2,FALSE()) -> 2 | H11: =VLOOKUP(C11,Tier_Constants!$A$3:$E$8,3,FALSE()) -> 8 | I11: =COUNTIF(Recipes!$B$3:$B$207,A11) -> 1 | J11: =COUNTIF(Recipes!$E$3:$E$207,A11)+COUNTIF(Recipes!$G$3:$G$207,A11) -> 6 | K11: =IF(COUNTIFS(Recipes!$B$3:$B$207,A11,Recipes!$I$3:$I$207,"<>simple")>0,"YES","") | L11: The first thing a new researcher learns to extract.
A12: T1_10 | B12: Titanium Dioxide | C12: 1 | E12: Ti | F12: 20 | G12: =VLOOKUP(C12,Tier_Constants!$A$3:$E$8,2,FALSE()) -> 2 | H12: =VLOOKUP(C12,Tier_Constants!$A$3:$E$8,3,FALSE()) -> 8 | I12: =COUNTIF(Recipes!$B$3:$B$207,A12) -> 1 | J12: =COUNTIF(Recipes!$E$3:$E$207,A12)+COUNTIF(Recipes!$G$3:$G$207,A12) -> 6 | K12: =IF(COUNTIFS(Recipes!$B$3:$B$207,A12,Recipes!$I$3:$I$207,"<>simple")>0,"YES","") | L12: Cheap, stable, and always in demand on the floor.
A13: T1_11 | B13: Manganese Dioxide | C13: 1 | E13: Mn | F13: 15 | G13: =VLOOKUP(C13,Tier_Constants!$A$3:$E$8,2,FALSE()) -> 2 | H13: =VLOOKUP(C13,Tier_Constants!$A$3:$E$8,3,FALSE()) -> 8 | I13: =COUNTIF(Recipes!$B$3:$B$207,A13) -> 1 | J13: =COUNTIF(Recipes!$E$3:$E$207,A13)+COUNTIF(Recipes!$G$3:$G$207,A13) -> 5 | K13: =IF(COUNTIFS(Recipes!$B$3:$B$207,A13,Recipes!$I$3:$I$207,"<>simple")>0,"YES","") | L13: Raw feedstock pulled straight from the extraction line.
A14: T1_12 | B14: Cobalt Chloride | C14: 1 | E14: Co | F14: 23 | G14: =VLOOKUP(C14,Tier_Constants!$A$3:$E$8,2,FALSE()) -> 2 | H14: =VLOOKUP(C14,Tier_Constants!$A$3:$E$8,3,FALSE()) -> 8 | I14: =COUNTIF(Recipes!$B$3:$B$207,A14) -> 1 | J14: =COUNTIF(Recipes!$E$3:$E$207,A14)+COUNTIF(Recipes!$G$3:$G$207,A14) -> 6 | K14: =IF(COUNTIFS(Recipes!$B$3:$B$207,A14,Recipes!$I$3:$I$207,"<>simple")>0,"YES","") | L14: A commodity-grade base material every lab burns through daily.
A15: T1_13 | B15: Nickel Sulfate | C15: 1 | E15: Ni | F15: 19 | G15: =VLOOKUP(C15,Tier_Constants!$A$3:$E$8,2,FALSE()) -> 2 | H15: =VLOOKUP(C15,Tier_Constants!$A$3:$E$8,3,FALSE()) -> 8 | I15: =COUNTIF(Recipes!$B$3:$B$207,A15) -> 1 | J15: =COUNTIF(Recipes!$E$3:$E$207,A15)+COUNTIF(Recipes!$G$3:$G$207,A15) -> 6 | K15: =IF(COUNTIFS(Recipes!$B$3:$B$207,A15,Recipes!$I$3:$I$207,"<>simple")>0,"YES","") | L15: Unremarkable on its own; indispensable in everything.
A16: T1_14 | B16: Barium Carbonate | C16: 1 | E16: Ba | F16: 17 | G16: =VLOOKUP(C16,Tier_Constants!$A$3:$E$8,2,FALSE()) -> 2 | H16: =VLOOKUP(C16,Tier_Constants!$A$3:$E$8,3,FALSE()) -> 8 | I16: =COUNTIF(Recipes!$B$3:$B$207,A16) -> 1 | J16: =COUNTIF(Recipes!$E$3:$E$207,A16)+COUNTIF(Recipes!$G$3:$G$207,A16) -> 5 | K16: =IF(COUNTIFS(Recipes!$B$3:$B$207,A16,Recipes!$I$3:$I$207,"<>simple")>0,"YES","") | L16: The first thing a new researcher learns to extract.
A17: T1_15 | B17: Strontium Carbonate | C17: 1 | E17: Sr | F17: 11 | G17: =VLOOKUP(C17,Tier_Constants!$A$3:$E$8,2,FALSE()) -> 2 | H17: =VLOOKUP(C17,Tier_Constants!$A$3:$E$8,3,FALSE()) -> 8 | I17: =COUNTIF(Recipes!$B$3:$B$207,A17) -> 1 | J17: =COUNTIF(Recipes!$E$3:$E$207,A17)+COUNTIF(Recipes!$G$3:$G$207,A17) -> 5 | K17: =IF(COUNTIFS(Recipes!$B$3:$B$207,A17,Recipes!$I$3:$I$207,"<>simple")>0,"YES","") | L17: Cheap, stable, and always in demand on the floor.
A18: T1_16 | B18: Lithium Carbonate | C18: 1 | E18: Li | F18: 15 | G18: =VLOOKUP(C18,Tier_Constants!$A$3:$E$8,2,FALSE()) -> 2 | H18: =VLOOKUP(C18,Tier_Constants!$A$3:$E$8,3,FALSE()) -> 8 | I18: =COUNTIF(Recipes!$B$3:$B$207,A18) -> 1 | J18: =COUNTIF(Recipes!$E$3:$E$207,A18)+COUNTIF(Recipes!$G$3:$G$207,A18) -> 5 | K18: =IF(COUNTIFS(Recipes!$B$3:$B$207,A18,Recipes!$I$3:$I$207,"<>simple")>0,"YES","") | L18: Raw feedstock pulled straight from the extraction line.
A19: T1_17 | B19: Chromium Oxide | C19: 1 | E19: Cr | F19: 16 | G19: =VLOOKUP(C19,Tier_Constants!$A$3:$E$8,2,FALSE()) -> 2 | H19: =VLOOKUP(C19,Tier_Constants!$A$3:$E$8,3,FALSE()) -> 8 | I19: =COUNTIF(Recipes!$B$3:$B$207,A19) -> 1 | J19: =COUNTIF(Recipes!$E$3:$E$207,A19)+COUNTIF(Recipes!$G$3:$G$207,A19) -> 7 | K19: =IF(COUNTIFS(Recipes!$B$3:$B$207,A19,Recipes!$I$3:$I$207,"<>simple")>0,"YES","") | L19: A commodity-grade base material every lab burns through daily.
... A152: T6_15 | B152: Picoscale Architect | C152: 6 | E152: (process/structure) | F152: 69000 | G152: =VLOOKUP(C152,Tier_Constants!$A$3:$E$8,2,FALSE()) -> 1440 | H152: =VLOOKUP(C152,Tier_Constants!$A$3:$E$8,3,FALSE()) -> 43 | I152: =COUNTIF(Recipes!$B$3:$B$207,A152) -> 1 | J152: =COUNTIF(Recipes!$E$3:$E$207,A152)+COUNTIF(Recipes!$G$3:$G$207,A152) -> 0 | K152: =IF(COUNTIFS(Recipes!$B$3:$B$207,A152,Recipes!$I$3:$I$207,"<>simple")>0,"YES","") | L152: Endgame chemistry; the dividend stream proves it.

Sheet Recipes
A1: RECIPE DATABASE — 205 mappings, element-conserving (metals from inputs; O/C/N/S/Cl/I/H/F are facility process feeds)
A2: Recipe ID | B2: Result ID | C2: Result name | D2: Result tier | E2: Input 1 ID | F2: Input 1 name | G2: Input 2 ID | H2: Input 2 name | I2: Pair type | J2: Variable pair ID | K2: Input class
A3: R001 | B3: T2_01 | C3: =VLOOKUP(B3,Compounds!$A$3:$B$152,2,FALSE()) -> Zinc Titanate | D3: =VLOOKUP(B3,Compounds!$A$3:$C$152,3,FALSE()) -> 2 | E3: T1_03 | F3: =VLOOKUP(E3,Compounds!$A$3:$B$152,2,FALSE()) -> Zinc Sulfate | G3: T1_10 | H3: =VLOOKUP(G3,Compounds!$A$3:$B$152,2,FALSE()) -> Titanium Dioxide | I3: simple | K3: T1+T1->T2
A4: R002 | B4: T2_03 | C4: =VLOOKUP(B4,Compounds!$A$3:$B$152,2,FALSE()) -> Calcium Silicate | D4: =VLOOKUP(B4,Compounds!$A$3:$C$152,3,FALSE()) -> 2 | E4: T1_02 | F4: =VLOOKUP(E4,Compounds!$A$3:$B$152,2,FALSE()) -> Calcium Oxide | G4: T1_09 | H4: =VLOOKUP(G4,Compounds!$A$3:$B$152,2,FALSE()) -> Silicon Dioxide | I4: simple | K4: T1+T1->T2
A5: R003 | B5: T2_04 | C5: =VLOOKUP(B5,Compounds!$A$3:$B$152,2,FALSE()) -> Sodium Aluminate | D5: =VLOOKUP(B5,Compounds!$A$3:$C$152,3,FALSE()) -> 2 | E5: T1_01 | F5: =VLOOKUP(E5,Compounds!$A$3:$B$152,2,FALSE()) -> Sodium Chloride | G5: T1_08 | H5: =VLOOKUP(G5,Compounds!$A$3:$B$152,2,FALSE()) -> Aluminum Oxide | I5: simple | K5: T1+T1->T2
A6: R004 | B6: T2_06 | C6: =VLOOKUP(B6,Compounds!$A$3:$B$152,2,FALSE()) -> Iron Phosphate | D6: =VLOOKUP(B6,Compounds!$A$3:$C$152,3,FALSE()) -> 2 | E6: T1_04 | F6: =VLOOKUP(E6,Compounds!$A$3:$B$152,2,FALSE()) -> Iron Acetate | G6: T1_30 | H6: =VLOOKUP(G6,Compounds!$A$3:$B$152,2,FALSE()) -> Sodium Phosphate | I6: simple | K6: T1+T1->T2
A7: R005 | B7: T2_07 | C7: =VLOOKUP(B7,Compounds!$A$3:$B$152,2,FALSE()) -> Magnesium Titanate | D7: =VLOOKUP(B7,Compounds!$A$3:$C$152,3,FALSE()) -> 2 | E7: T1_06 | F7: =VLOOKUP(E7,Compounds!$A$3:$B$152,2,FALSE()) -> Magnesium Chloride | G7: T1_10 | H7: =VLOOKUP(G7,Compounds!$A$3:$B$152,2,FALSE()) -> Titanium Dioxide | I7: simple | K7: T1+T1->T2
A8: R006 | B8: T2_08 | C8: =VLOOKUP(B8,Compounds!$A$3:$B$152,2,FALSE()) -> Barium Titanate | D8: =VLOOKUP(B8,Compounds!$A$3:$C$152,3,FALSE()) -> 2 | E8: T1_10 | F8: =VLOOKUP(E8,Compounds!$A$3:$B$152,2,FALSE()) -> Titanium Dioxide | G8: T1_14 | H8: =VLOOKUP(G8,Compounds!$A$3:$B$152,2,FALSE()) -> Barium Carbonate | I8: simple | K8: T1+T1->T2
A9: R007 | B9: T2_09 | C9: =VLOOKUP(B9,Compounds!$A$3:$B$152,2,FALSE()) -> Lithium Phosphate | D9: =VLOOKUP(B9,Compounds!$A$3:$C$152,3,FALSE()) -> 2 | E9: T1_16 | F9: =VLOOKUP(E9,Compounds!$A$3:$B$152,2,FALSE()) -> Lithium Carbonate | G9: T1_30 | H9: =VLOOKUP(G9,Compounds!$A$3:$B$152,2,FALSE()) -> Sodium Phosphate | I9: simple | K9: T1+T1->T2
A10: R008 | B10: T2_12 | C10: =VLOOKUP(B10,Compounds!$A$3:$B$152,2,FALSE()) -> Manganese Ferrite | D10: =VLOOKUP(B10,Compounds!$A$3:$C$152,3,FALSE()) -> 2 | E10: T1_04 | F10: =VLOOKUP(E10,Compounds!$A$3:$B$152,2,FALSE()) -> Iron Acetate | G10: T1_11 | H10: =VLOOKUP(G10,Compounds!$A$3:$B$152,2,FALSE()) -> Manganese Dioxide | I10: simple | K10: T1+T1->T2
A11: R009 | B11: T2_13 | C11: =VLOOKUP(B11,Compounds!$A$3:$B$152,2,FALSE()) -> Zinc Ferrite | D11: =VLOOKUP(B11,Compounds!$A$3:$C$152,3,FALSE()) -> 2 | E11: T1_03 | F11: =VLOOKUP(E11,Compounds!$A$3:$B$152,2,FALSE()) -> Zinc Sulfate | G11: T1_04 | H11: =VLOOKUP(G11,Compounds!$A$3:$B$152,2,FALSE()) -> Iron Acetate | I11: simple | K11: T1+T1->T2
A12: R010 | B12: T2_17 | C12: =VLOOKUP(B12,Compounds!$A$3:$B$152,2,FALSE()) -> Potassium Silicate | D12: =VLOOKUP(B12,Compounds!$A$3:$C$152,3,FALSE()) -> 2 | E12: T1_05 | F12: =VLOOKUP(E12,Compounds!$A$3:$B$152,2,FALSE()) -> Potassium Iodide | G12: T1_22 | H12: =VLOOKUP(G12,Compounds!$A$3:$B$152,2,FALSE()) -> Zirconium Silicate | I12: simple | K12: T1+T1->T2
A13: R011 | B13: T2_18 | C13: =VLOOKUP(B13,Compounds!$A$3:$B$152,2,FALSE()) -> Copper Aluminate | D13: =VLOOKUP(B13,Compounds!$A$3:$C$152,3,FALSE()) -> 2 | E13: T1_07 | F13: =VLOOKUP(E13,Compounds!$A$3:$B$152,2,FALSE()) -> Copper Sulfate | G13: T1_08 | H13: =VLOOKUP(G13,Compounds!$A$3:$B$152,2,FALSE()) -> Aluminum Oxide | I13: simple | K13: T1+T1->T2
A14: R012 | B14: T2_19 | C14: =VLOOKUP(B14,Compounds!$A$3:$B$152,2,FALSE()) -> Iron Silicide | D14: =VLOOKUP(B14,Compounds!$A$3:$C$152,3,FALSE()) -> 2 | E14: T1_04 | F14: =VLOOKUP(E14,Compounds!$A$3:$B$152,2,FALSE()) -> Iron Acetate | G14: T1_09 | H14: =VLOOKUP(G14,Compounds!$A$3:$B$152,2,FALSE()) -> Silicon Dioxide | I14: simple | K14: T1+T1->T2
... A97: R095 | B97: T3_28 | C97: =VLOOKUP(B97,Compounds!$A$3:$B$152,2,FALSE()) -> Niobium Carbide | D97: =VLOOKUP(B97,Compounds!$A$3:$C$152,3,FALSE()) -> 3 | E97: T2_22 | F97: =VLOOKUP(E97,Compounds!$A$3:$B$152,2,FALSE()) -> Strontium Titanate | G97: T2_23 | H97: =VLOOKUP(G97,Compounds!$A$3:$B$152,2,FALSE()) -> Lithium Niobate | I97: simple | K97: T2+T2->T3
A98: R096 | B98: T3_05 | C98: =VLOOKUP(B98,Compounds!$A$3:$B$152,2,FALSE()) -> Zirconium Carbide | D98: =VLOOKUP(B98,Compounds!$A$3:$C$152,3,FALSE()) -> 3 | E98: T1_22 | F98: =VLOOKUP(E98,Compounds!$A$3:$B$152,2,FALSE()) -> Zirconium Silicate | G98: T2_25 | H98: =VLOOKUP(G98,Compounds!$A$3:$B$152,2,FALSE()) -> Sodium Tungstate | I98: variable-primary | J98: V3_01 | K98: T1+T2->T3
A99: R097 | B99: T3_06 | C99: =VLOOKUP(B99,Compounds!$A$3:$B$152,2,FALSE()) -> Tungsten Carbide | D99: =VLOOKUP(B99,Compounds!$A$3:$C$152,3,FALSE()) -> 3 | E99: T1_22 | F99: =VLOOKUP(E99,Compounds!$A$3:$B$152,2,FALSE()) -> Zirconium Silicate | G99: T2_25 | H99: =VLOOKUP(G99,Compounds!$A$3:$B$152,2,FALSE()) -> Sodium Tungstate | I99: variable-alternate | J99: V3_01 | K99: T1+T2->T3
A100: R098 | B100: T3_28 | C100: =VLOOKUP(B100,Compounds!$A$3:$B$152,2,FALSE()) -> Niobium Carbide | D100: =VLOOKUP(B100,Compounds!$A$3:$C$152,3,FALSE()) -> 3 | E100: T1_23 | F100: =VLOOKUP(E100,Compounds!$A$3:$B$152,2,FALSE()) -> Niobium Pentoxide | G100: T2_21 | H100: =VLOOKUP(G100,Compounds!$A$3:$B$152,2,FALSE()) -> Calcium Zirconate | I100: variable-primary | J100: V3_02 | K100: T1+T2->T3
A101: R099 | B101: T3_05 | C101: =VLOOKUP(B101,Compounds!$A$3:$B$152,2,FALSE()) -> Zirconium Carbide | D101: =VLOOKUP(B101,Compounds!$A$3:$C$152,3,FALSE()) -> 3 | E101: T1_23 | F101: =VLOOKUP(E101,Compounds!$A$3:$B$152,2,FALSE()) -> Niobium Pentoxide | G101: T2_21 | H101: =VLOOKUP(G101,Compounds!$A$3:$B$152,2,FALSE()) -> Calcium Zirconate | I101: variable-alternate | J101: V3_02 | K101: T1+T2->T3
A102: R100 | B102: T3_01 | C102: =VLOOKUP(B102,Compounds!$A$3:$B$152,2,FALSE()) -> Borosilicate Glass | D102: =VLOOKUP(B102,Compounds!$A$3:$C$152,3,FALSE()) -> 3 | E102: T1_28 | F102: =VLOOKUP(E102,Compounds!$A$3:$B$152,2,FALSE()) -> Sodium Borate | G102: T2_14 | H102: =VLOOKUP(G102,Compounds!$A$3:$B$152,2,FALSE()) -> Silicon Carbide | I102: simple | K102: T1+T2->T3
A103: R101 | B103: T3_02 | C103: =VLOOKUP(B103,Compounds!$A$3:$B$152,2,FALSE()) -> Ferrochrome Alloy | D103: =VLOOKUP(B103,Compounds!$A$3:$C$152,3,FALSE()) -> 3 | E103: T1_17 | F103: =VLOOKUP(E103,Compounds!$A$3:$B$152,2,FALSE()) -> Chromium Oxide | G103: T2_24 | H103: =VLOOKUP(G103,Compounds!$A$3:$B$152,2,FALSE()) -> Barium Ferrite | I103: simple | K103: T1+T2->T3
A104: R102 | B104: T3_03 | C104: =VLOOKUP(B104,Compounds!$A$3:$B$152,2,FALSE()) -> Cupronickel Matrix | D104: =VLOOKUP(B104,Compounds!$A$3:$C$152,3,FALSE()) -> 3 | E104: T1_07 | F104: =VLOOKUP(E104,Compounds!$A$3:$B$152,2,FALSE()) -> Copper Sulfate | G104: T2_10 | H104: =VLOOKUP(G104,Compounds!$A$3:$B$152,2,FALSE()) -> Nickel Carbonate | I104: simple | K104: T1+T2->T3
A105: R103 | B105: T3_06 | C105: =VLOOKUP(B105,Compounds!$A$3:$B$152,2,FALSE()) -> Tungsten Carbide | D105: =VLOOKUP(B105,Compounds!$A$3:$C$152,3,FALSE()) -> 3 | E105: T2_21 | F105: =VLOOKUP(E105,Compounds!$A$3:$B$152,2,FALSE()) -> Calcium Zirconate | G105: T2_25 | H105: =VLOOKUP(G105,Compounds!$A$3:$B$152,2,FALSE()) -> Sodium Tungstate | I105: variable-primary | J105: V3_03 | K105: T2+T2->T3
A106: R104 | B106: T3_05 | C106: =VLOOKUP(B106,Compounds!$A$3:$B$152,2,FALSE()) -> Zirconium Carbide | D106: =VLOOKUP(B106,Compounds!$A$3:$C$152,3,FALSE()) -> 3 | E106: T2_21 | F106: =VLOOKUP(E106,Compounds!$A$3:$B$152,2,FALSE()) -> Calcium Zirconate | G106: T2_25 | H106: =VLOOKUP(G106,Compounds!$A$3:$B$152,2,FALSE()) -> Sodium Tungstate | I106: variable-alternate | J106: V3_03 | K106: T2+T2->T3
A107: R105 | B107: T3_28 | C107: =VLOOKUP(B107,Compounds!$A$3:$B$152,2,FALSE()) -> Niobium Carbide | D107: =VLOOKUP(B107,Compounds!$A$3:$C$152,3,FALSE()) -> 3 | E107: T2_21 | F107: =VLOOKUP(E107,Compounds!$A$3:$B$152,2,FALSE()) -> Calcium Zirconate | G107: T2_23 | H107: =VLOOKUP(G107,Compounds!$A$3:$B$152,2,FALSE()) -> Lithium Niobate | I107: variable-primary | J107: V3_04 | K107: T2+T2->T3
A108: R106 | B108: T3_05 | C108: =VLOOKUP(B108,Compounds!$A$3:$B$152,2,FALSE()) -> Zirconium Carbide | D108: =VLOOKUP(B108,Compounds!$A$3:$C$152,3,FALSE()) -> 3 | E108: T2_21 | F108: =VLOOKUP(E108,Compounds!$A$3:$B$152,2,FALSE()) -> Calcium Zirconate | G108: T2_23 | H108: =VLOOKUP(G108,Compounds!$A$3:$B$152,2,FALSE()) -> Lithium Niobate | I108: variable-alternate | J108: V3_04 | K108: T2+T2->T3
A109: R107 | B109: T3_06 | C109: =VLOOKUP(B109,Compounds!$A$3:$B$152,2,FALSE()) -> Tungsten Carbide | D109: =VLOOKUP(B109,Compounds!$A$3:$C$152,3,FALSE()) -> 3 | E109: T2_25 | F109: =VLOOKUP(E109,Compounds!$A$3:$B$152,2,FALSE()) -> Sodium Tungstate | G109: T2_30 | H109: =VLOOKUP(G109,Compounds!$A$3:$B$152,2,FALSE()) -> Yttrium Aluminate | I109: variable-primary | J109: V3_05 | K109: T2+T2->T3
A110: R108 | B110: T3_10 | C110: =VLOOKUP(B110,Compounds!$A$3:$B$152,2,FALSE()) -> Yttrium Garnet | D110: =VLOOKUP(B110,Compounds!$A$3:$C$152,3,FALSE()) -> 3 | E110: T2_25 | F110: =VLOOKUP(E110,Compounds!$A$3:$B$152,2,FALSE()) -> Sodium Tungstate | G110: T2_30 | H110: =VLOOKUP(G110,Compounds!$A$3:$B$152,2,FALSE()) -> Yttrium Aluminate | I110: variable-alternate | J110: V3_05 | K110: T2+T2->T3
A111: R109 | B111: T3_28 | C111: =VLOOKUP(B111,Compounds!$A$3:$B$152,2,FALSE()) -> Niobium Carbide | D111: =VLOOKUP(B111,Compounds!$A$3:$C$152,3,FALSE()) -> 3 | E111: T2_01 | F111: =VLOOKUP(E111,Compounds!$A$3:$B$152,2,FALSE()) -> Zinc Titanate | G111: T2_23 | H111: =VLOOKUP(G111,Compounds!$A$3:$B$152,2,FALSE()) -> Lithium Niobate | I111: variable-primary | J111: V3_06 | K111: T2+T2->T3
A112: R110 | B112: T3_17 | C112: =VLOOKUP(B112,Compounds!$A$3:$B$152,2,FALSE()) -> Lithium Titanate Spinel | D112: =VLOOKUP(B112,Compounds!$A$3:$C$152,3,FALSE()) -> 3 | E112: T2_01 | F112: =VLOOKUP(E112,Compounds!$A$3:$B$152,2,FALSE()) -> Zinc Titanate | G112: T2_23 | H112: =VLOOKUP(G112,Compounds!$A$3:$B$152,2,FALSE()) -> Lithium Niobate | I112: variable-alternate | J112: V3_06 | K112: T2+T2->T3
A113: R111 | B113: T3_06 | C113: =VLOOKUP(B113,Compounds!$A$3:$B$152,2,FALSE()) -> Tungsten Carbide | D113: =VLOOKUP(B113,Compounds!$A$3:$C$152,3,FALSE()) -> 3 | E113: T2_02 | F113: =VLOOKUP(E113,Compounds!$A$3:$B$152,2,FALSE()) -> Zinc Salt | G113: T2_25 | H113: =VLOOKUP(G113,Compounds!$A$3:$B$152,2,FALSE()) -> Sodium Tungstate | I113: variable-primary | J113: V3_07 | K113: T2+T2->T3
A114: R112 | B114: T3_21 | C114: =VLOOKUP(B114,Compounds!$A$3:$B$152,2,FALSE()) -> Tungsten Bronze | D114: =VLOOKUP(B114,Compounds!$A$3:$C$152,3,FALSE()) -> 3 | E114: T2_02 | F114: =VLOOKUP(E114,Compounds!$A$3:$B$152,2,FALSE()) -> Zinc Salt | G114: T2_25 | H114: =VLOOKUP(G114,Compounds!$A$3:$B$152,2,FALSE()) -> Sodium Tungstate | I114: variable-alternate | J114: V3_07 | K114: T2+T2->T3
A115: R113 | B115: T3_04 | C115: =VLOOKUP(B115,Compounds!$A$3:$B$152,2,FALSE()) -> Titanium Aluminide | D115: =VLOOKUP(B115,Compounds!$A$3:$C$152,3,FALSE()) -> 3 | E115: T2_07 | F115: =VLOOKUP(E115,Compounds!$A$3:$B$152,2,FALSE()) -> Magnesium Titanate | G115: T2_15 | H115: =VLOOKUP(G115,Compounds!$A$3:$B$152,2,FALSE()) -> Aluminum Nitride | I115: simple | K115: T2+T2->T3
A116: R114 | B116: T3_07 | C116: =VLOOKUP(B116,Compounds!$A$3:$B$152,2,FALSE()) -> Cobalt Aluminate | D116: =VLOOKUP(B116,Compounds!$A$3:$C$152,3,FALSE()) -> 3 | E116: T2_04 | F116: =VLOOKUP(E116,Compounds!$A$3:$B$152,2,FALSE()) -> Sodium Aluminate | G116: T2_11 | H116: =VLOOKUP(G116,Compounds!$A$3:$B$152,2,FALSE()) -> Cobalt Sulfide | I116: simple | K116: T2+T2->T3
A117: R115 | B117: T3_08 | C117: =VLOOKUP(B117,Compounds!$A$3:$B$152,2,FALSE()) -> Nickel Superalloy | D117: =VLOOKUP(B117,Compounds!$A$3:$C$152,3,FALSE()) -> 3 | E117: T2_10 | F117: =VLOOKUP(E117,Compounds!$A$3:$B$152,2,FALSE()) -> Nickel Carbonate | G117: T2_28 | H117: =VLOOKUP(G117,Compounds!$A$3:$B$152,2,FALSE()) -> Chromium Nitride | I117: simple | K117: T2+T2->T3
A118: R116 | B118: T4_05 | C118: =VLOOKUP(B118,Compounds!$A$3:$B$152,2,FALSE()) -> Amorphous Ferrosilicon | D118: =VLOOKUP(B118,Compounds!$A$3:$C$152,3,FALSE()) -> 4 | E118: T2_03 | F118: =VLOOKUP(E118,Compounds!$A$3:$B$152,2,FALSE()) -> Calcium Silicate | G118: T3_02 | H118: =VLOOKUP(G118,Compounds!$A$3:$B$152,2,FALSE()) -> Ferrochrome Alloy | I118: simple | K118: T2+T3->T4
A119: R117 | B119: T4_12 | C119: =VLOOKUP(B119,Compounds!$A$3:$B$152,2,FALSE()) -> Metallic Glass | D119: =VLOOKUP(B119,Compounds!$A$3:$C$152,3,FALSE()) -> 4 | E119: T2_05 | F119: =VLOOKUP(E119,Compounds!$A$3:$B$152,2,FALSE()) -> Copper Carbonate | G119: T3_05 | H119: =VLOOKUP(G119,Compounds!$A$3:$B$152,2,FALSE()) -> Zirconium Carbide | I119: simple | K119: T2+T3->T4
A120: R118 | B120: T4_13 | C120: =VLOOKUP(B120,Compounds!$A$3:$B$152,2,FALSE()) -> Shape-Memory Nitinol | D120: =VLOOKUP(B120,Compounds!$A$3:$C$152,3,FALSE()) -> 4 | E120: T2_06 | F120: =VLOOKUP(E120,Compounds!$A$3:$B$152,2,FALSE()) -> Iron Phosphate | G120: T3_24 | H120: =VLOOKUP(G120,Compounds!$A$3:$B$152,2,FALSE()) -> Nickel-Titanium Ingot | I120: simple | K120: T2+T3->T4
A121: R119 | B121: T4_18 | C121: =VLOOKUP(B121,Compounds!$A$3:$B$152,2,FALSE()) -> Photoluminescent Phosphor | D121: =VLOOKUP(B121,Compounds!$A$3:$C$152,3,FALSE()) -> 4 | E121: T2_29 | F121: =VLOOKUP(E121,Compounds!$A$3:$B$152,2,FALSE()) -> Cerium Phosphate | G121: T3_10 | H121: =VLOOKUP(G121,Compounds!$A$3:$B$152,2,FALSE()) -> Yttrium Garnet | I121: simple | K121: T2+T3->T4
A122: R120 | B122: T4_19 | C122: =VLOOKUP(B122,Compounds!$A$3:$B$152,2,FALSE()) -> Dielectric Ceramite | D122: =VLOOKUP(B122,Compounds!$A$3:$C$152,3,FALSE()) -> 4 | E122: T2_08 | F122: =VLOOKUP(E122,Compounds!$A$3:$B$152,2,FALSE()) -> Barium Titanate | G122: T3_01 | H122: =VLOOKUP(G122,Compounds!$A$3:$B$152,2,FALSE()) -> Borosilicate Glass | I122: simple | K122: T2+T3->T4
A123: R121 | B123: T4_23 | C123: =VLOOKUP(B123,Compounds!$A$3:$B$152,2,FALSE()) -> Magnetocaloric Alloy | D123: =VLOOKUP(B123,Compounds!$A$3:$C$152,3,FALSE()) -> 4 | E123: T2_13 | F123: =VLOOKUP(E123,Compounds!$A$3:$B$152,2,FALSE()) -> Zinc Ferrite | G123: T3_09 | H123: =VLOOKUP(G123,Compounds!$A$3:$B$152,2,FALSE()) -> Lanthanum Aluminate | I123: simple | K123: T2+T3->T4
A124: R122 | B124: T4_01 | C124: =VLOOKUP(B124,Compounds!$A$3:$B$152,2,FALSE()) -> Synthetic Corundum | D124: =VLOOKUP(B124,Compounds!$A$3:$C$152,3,FALSE()) -> 4 | E124: T2_09 | F124: =VLOOKUP(E124,Compounds!$A$3:$B$152,2,FALSE()) -> Lithium Phosphate | G124: T3_04 | H124: =VLOOKUP(G124,Compounds!$A$3:$B$152,2,FALSE()) -> Titanium Aluminide | I124: simple | K124: T2+T3->T4
A125: R123 | B125: T4_02 | C125: =VLOOKUP(B125,Compounds!$A$3:$B$152,2,FALSE()) -> Cubic Boron Nitride | D125: =VLOOKUP(B125,Compounds!$A$3:$C$152,3,FALSE()) -> 4 | E125: T2_16 | F125: =VLOOKUP(E125,Compounds!$A$3:$B$152,2,FALSE()) -> Titanium Carbide | G125: T3_26 | H125: =VLOOKUP(G125,Compounds!$A$3:$B$152,2,FALSE()) -> Calcium Hexaboride | I125: simple | K125: T2+T3->T4
A126: R124 | B126: T4_04 | C126: =VLOOKUP(B126,Compounds!$A$3:$B$152,2,FALSE()) -> Fused Silica Composite | D126: =VLOOKUP(B126,Compounds!$A$3:$C$152,3,FALSE()) -> 4 | E126: T2_17 | F126: =VLOOKUP(E126,Compounds!$A$3:$B$152,2,FALSE()) -> Potassium Silicate | G126: T3_03 | H126: =VLOOKUP(G126,Compounds!$A$3:$B$152,2,FALSE()) -> Cupronickel Matrix | I126: simple | K126: T2+T3->T4
... A142: R140 | B142: T4_22 | C142: =VLOOKUP(B142,Compounds!$A$3:$B$152,2,FALSE()) -> Conductive Polymer Base | D142: =VLOOKUP(B142,Compounds!$A$3:$C$152,3,FALSE()) -> 4 | E142: T3_25 | F142: =VLOOKUP(E142,Compounds!$A$3:$B$152,2,FALSE()) -> Cerium Zirconate | G142: T3_29 | H142: =VLOOKUP(G142,Compounds!$A$3:$B$152,2,FALSE()) -> Sodium Niobate | I142: simple | K142: T3+T3->T4
A143: R141 | B143: T4_03 | C143: =VLOOKUP(B143,Compounds!$A$3:$B$152,2,FALSE()) -> Pyrolytic Graphite | D143: =VLOOKUP(B143,Compounds!$A$3:$C$152,3,FALSE()) -> 4 | E143: T2_11 | F143: =VLOOKUP(E143,Compounds!$A$3:$B$152,2,FALSE()) -> Cobalt Sulfide | G143: T3_30 | H143: =VLOOKUP(G143,Compounds!$A$3:$B$152,2,FALSE()) -> Lanthanum Manganite | I143: variable-primary | J143: V4_01 | K143: T2+T3->T4
A144: R142 | B144: T4_10 | C144: =VLOOKUP(B144,Compounds!$A$3:$B$152,2,FALSE()) -> Carbon Nanoweave | D144: =VLOOKUP(B144,Compounds!$A$3:$C$152,3,FALSE()) -> 4 | E144: T2_11 | F144: =VLOOKUP(E144,Compounds!$A$3:$B$152,2,FALSE()) -> Cobalt Sulfide | G144: T3_30 | H144: =VLOOKUP(G144,Compounds!$A$3:$B$152,2,FALSE()) -> Lanthanum Manganite | I144: variable-alternate | J144: V4_01 | K144: T2+T3->T4
A145: R143 | B145: T4_22 | C145: =VLOOKUP(B145,Compounds!$A$3:$B$152,2,FALSE()) -> Conductive Polymer Base | D145: =VLOOKUP(B145,Compounds!$A$3:$C$152,3,FALSE()) -> 4 | E145: T2_12 | F145: =VLOOKUP(E145,Compounds!$A$3:$B$152,2,FALSE()) -> Manganese Ferrite | G145: T3_02 | H145: =VLOOKUP(G145,Compounds!$A$3:$B$152,2,FALSE()) -> Ferrochrome Alloy | I145: variable-primary | J145: V4_02 | K145: T2+T3->T4
A146: R144 | B146: T4_03 | C146: =VLOOKUP(B146,Compounds!$A$3:$B$152,2,FALSE()) -> Pyrolytic Graphite | D146: =VLOOKUP(B146,Compounds!$A$3:$C$152,3,FALSE()) -> 4 | E146: T2_12 | F146: =VLOOKUP(E146,Compounds!$A$3:$B$152,2,FALSE()) -> Manganese Ferrite | G146: T3_02 | H146: =VLOOKUP(G146,Compounds!$A$3:$B$152,2,FALSE()) -> Ferrochrome Alloy | I146: variable-alternate | J146: V4_02 | K146: T2+T3->T4
A147: R145 | B147: T4_01 | C147: =VLOOKUP(B147,Compounds!$A$3:$B$152,2,FALSE()) -> Synthetic Corundum | D147: =VLOOKUP(B147,Compounds!$A$3:$C$152,3,FALSE()) -> 4 | E147: T2_13 | F147: =VLOOKUP(E147,Compounds!$A$3:$B$152,2,FALSE()) -> Zinc Ferrite | G147: T3_04 | H147: =VLOOKUP(G147,Compounds!$A$3:$B$152,2,FALSE()) -> Titanium Aluminide | I147: simple | K147: T2+T3->T4
A148: R146 | B148: T4_02 | C148: =VLOOKUP(B148,Compounds!$A$3:$B$152,2,FALSE()) -> Cubic Boron Nitride | D148: =VLOOKUP(B148,Compounds!$A$3:$C$152,3,FALSE()) -> 4 | E148: T2_20 | F148: =VLOOKUP(E148,Compounds!$A$3:$B$152,2,FALSE()) -> Magnesium Borate | G148: T3_03 | H148: =VLOOKUP(G148,Compounds!$A$3:$B$152,2,FALSE()) -> Cupronickel Matrix | I148: simple | K148: T2+T3->T4
A149: R147 | B149: T4_04 | C149: =VLOOKUP(B149,Compounds!$A$3:$B$152,2,FALSE()) -> Fused Silica Composite | D149: =VLOOKUP(B149,Compounds!$A$3:$C$152,3,FALSE()) -> 4 | E149: T2_14 | F149: =VLOOKUP(E149,Compounds!$A$3:$B$152,2,FALSE()) -> Silicon Carbide | G149: T3_05 | H149: =VLOOKUP(G149,Compounds!$A$3:$B$152,2,FALSE()) -> Zirconium Carbide | I149: simple | K149: T2+T3->T4
A150: R148 | B150: T4_05 | C150: =VLOOKUP(B150,Compounds!$A$3:$B$152,2,FALSE()) -> Amorphous Ferrosilicon | D150: =VLOOKUP(B150,Compounds!$A$3:$C$152,3,FALSE()) -> 4 | E150: T2_17 | F150: =VLOOKUP(E150,Compounds!$A$3:$B$152,2,FALSE()) -> Potassium Silicate | G150: T3_19 | H150: =VLOOKUP(G150,Compounds!$A$3:$B$152,2,FALSE()) -> Strontium Ferrite | I150: simple | K150: T2+T3->T4
A151: R149 | B151: T4_10 | C151: =VLOOKUP(B151,Compounds!$A$3:$B$152,2,FALSE()) -> Carbon Nanoweave | D151: =VLOOKUP(B151,Compounds!$A$3:$C$152,3,FALSE()) -> 4 | E151: T3_06 | F151: =VLOOKUP(E151,Compounds!$A$3:$B$152,2,FALSE()) -> Tungsten Carbide | G151: T3_07 | H151: =VLOOKUP(G151,Compounds!$A$3:$B$152,2,FALSE()) -> Cobalt Aluminate | I151: variable-primary | J151: V4_03 | K151: T3+T3->T4
A152: R150 | B152: T4_22 | C152: =VLOOKUP(B152,Compounds!$A$3:$B$152,2,FALSE()) -> Conductive Polymer Base | D152: =VLOOKUP(B152,Compounds!$A$3:$C$152,3,FALSE()) -> 4 | E152: T3_06 | F152: =VLOOKUP(E152,Compounds!$A$3:$B$152,2,FALSE()) -> Tungsten Carbide | G152: T3_07 | H152: =VLOOKUP(G152,Compounds!$A$3:$B$152,2,FALSE()) -> Cobalt Aluminate | I152: variable-alternate | J152: V4_03 | K152: T3+T3->T4
A153: R151 | B153: T4_03 | C153: =VLOOKUP(B153,Compounds!$A$3:$B$152,2,FALSE()) -> Pyrolytic Graphite | D153: =VLOOKUP(B153,Compounds!$A$3:$C$152,3,FALSE()) -> 4 | E153: T3_08 | F153: =VLOOKUP(E153,Compounds!$A$3:$B$152,2,FALSE()) -> Nickel Superalloy | G153: T3_09 | H153: =VLOOKUP(G153,Compounds!$A$3:$B$152,2,FALSE()) -> Lanthanum Aluminate | I153: variable-primary | J153: V4_04 | K153: T3+T3->T4
A154: R152 | B154: T4_10 | C154: =VLOOKUP(B154,Compounds!$A$3:$B$152,2,FALSE()) -> Carbon Nanoweave | D154: =VLOOKUP(B154,Compounds!$A$3:$C$152,3,FALSE()) -> 4 | E154: T3_08 | F154: =VLOOKUP(E154,Compounds!$A$3:$B$152,2,FALSE()) -> Nickel Superalloy | G154: T3_09 | H154: =VLOOKUP(G154,Compounds!$A$3:$B$152,2,FALSE()) -> Lanthanum Aluminate | I154: variable-alternate | J154: V4_04 | K154: T3+T3->T4
A155: R153 | B155: T4_22 | C155: =VLOOKUP(B155,Compounds!$A$3:$B$152,2,FALSE()) -> Conductive Polymer Base | D155: =VLOOKUP(B155,Compounds!$A$3:$C$152,3,FALSE()) -> 4 | E155: T3_10 | F155: =VLOOKUP(E155,Compounds!$A$3:$B$152,2,FALSE()) -> Yttrium Garnet | G155: T3_11 | H155: =VLOOKUP(G155,Compounds!$A$3:$B$152,2,FALSE()) -> Bismuth Vanadate | I155: variable-primary | J155: V4_05 | K155: T3+T3->T4
A156: R154 | B156: T4_03 | C156: =VLOOKUP(B156,Compounds!$A$3:$B$152,2,FALSE()) -> Pyrolytic Graphite | D156: =VLOOKUP(B156,Compounds!$A$3:$C$152,3,FALSE()) -> 4 | E156: T3_10 | F156: =VLOOKUP(E156,Compounds!$A$3:$B$152,2,FALSE()) -> Yttrium Garnet | G156: T3_11 | H156: =VLOOKUP(G156,Compounds!$A$3:$B$152,2,FALSE()) -> Bismuth Vanadate | I156: variable-alternate | J156: V4_05 | K156: T3+T3->T4
A157: R155 | B157: T4_10 | C157: =VLOOKUP(B157,Compounds!$A$3:$B$152,2,FALSE()) -> Carbon Nanoweave | D157: =VLOOKUP(B157,Compounds!$A$3:$C$152,3,FALSE()) -> 4 | E157: T3_12 | F157: =VLOOKUP(E157,Compounds!$A$3:$B$152,2,FALSE()) -> Molybdenum Disilicide | G157: T3_13 | H157: =VLOOKUP(G157,Compounds!$A$3:$B$152,2,FALSE()) -> Chromium Silicide | I157: variable-primary | J157: V4_06 | K157: T3+T3->T4
A158: R156 | B158: T4_22 | C158: =VLOOKUP(B158,Compounds!$A$3:$B$152,2,FALSE()) -> Conductive Polymer Base | D158: =VLOOKUP(B158,Compounds!$A$3:$C$152,3,FALSE()) -> 4 | E158: T3_12 | F158: =VLOOKUP(E158,Compounds!$A$3:$B$152,2,FALSE()) -> Molybdenum Disilicide | G158: T3_13 | H158: =VLOOKUP(G158,Compounds!$A$3:$B$152,2,FALSE()) -> Chromium Silicide | I158: variable-alternate | J158: V4_06 | K158: T3+T3->T4
A159: R157 | B159: T4_06 | C159: =VLOOKUP(B159,Compounds!$A$3:$B$152,2,FALSE()) -> Single-Crystal Sapphire | D159: =VLOOKUP(B159,Compounds!$A$3:$C$152,3,FALSE()) -> 4 | E159: T3_14 | F159: =VLOOKUP(E159,Compounds!$A$3:$B$152,2,FALSE()) -> Manganese Bronze | G159: T3_16 | H159: =VLOOKUP(G159,Compounds!$A$3:$B$152,2,FALSE()) -> Magnesium Spinel | I159: simple | K159: T3+T3->T4
A160: R158 | B160: T4_07 | C160: =VLOOKUP(B160,Compounds!$A$3:$B$152,2,FALSE()) -> Stabilized Zirconia | D160: =VLOOKUP(B160,Compounds!$A$3:$C$152,3,FALSE()) -> 4 | E160: T3_15 | F160: =VLOOKUP(E160,Compounds!$A$3:$B$152,2,FALSE()) -> Phosphor Bronze | G160: T3_18 | H160: =VLOOKUP(G160,Compounds!$A$3:$B$152,2,FALSE()) -> Barium Zirconate | I160: simple | K160: T3+T3->T4
A161: R159 | B161: T4_08 | C161: =VLOOKUP(B161,Compounds!$A$3:$B$152,2,FALSE()) -> Photonic Silica | D161: =VLOOKUP(B161,Compounds!$A$3:$C$152,3,FALSE()) -> 4 | E161: T3_01 | F161: =VLOOKUP(E161,Compounds!$A$3:$B$152,2,FALSE()) -> Borosilicate Glass | G161: T3_17 | H161: =VLOOKUP(G161,Compounds!$A$3:$B$152,2,FALSE()) -> Lithium Titanate Spinel | I161: simple | K161: T3+T3->T4
A162: R160 | B162: T4_09 | C162: =VLOOKUP(B162,Compounds!$A$3:$B$152,2,FALSE()) -> Superconducting Niobate | D162: =VLOOKUP(B162,Compounds!$A$3:$C$152,3,FALSE()) -> 4 | E162: T3_20 | F162: =VLOOKUP(E162,Compounds!$A$3:$B$152,2,FALSE()) -> Zinc Stannate | G162: T3_28 | H162: =VLOOKUP(G162,Compounds!$A$3:$B$152,2,FALSE()) -> Niobium Carbide | I162: simple | K162: T3+T3->T4
A163: R161 | B163: T5_09 | C163: =VLOOKUP(B163,Compounds!$A$3:$B$152,2,FALSE()) -> Spintronic Alloy | D163: =VLOOKUP(B163,Compounds!$A$3:$C$152,3,FALSE()) -> 5 | E163: T3_23 | F163: =VLOOKUP(E163,Compounds!$A$3:$B$152,2,FALSE()) -> Cobalt Ferrite | G163: T4_01 | H163: =VLOOKUP(G163,Compounds!$A$3:$B$152,2,FALSE()) -> Synthetic Corundum | I163: simple | K163: T3+T4->T5
A164: R162 | B164: T5_17 | C164: =VLOOKUP(B164,Compounds!$A$3:$B$152,2,FALSE()) -> Perovskite Cell | D164: =VLOOKUP(B164,Compounds!$A$3:$C$152,3,FALSE()) -> 5 | E164: T3_24 | F164: =VLOOKUP(E164,Compounds!$A$3:$B$152,2,FALSE()) -> Nickel-Titanium Ingot | G164: T4_20 | H164: =VLOOKUP(G164,Compounds!$A$3:$B$152,2,FALSE()) -> Optical Fluorite | I164: simple | K164: T3+T4->T5
A165: R163 | B165: T5_01 | C165: =VLOOKUP(B165,Compounds!$A$3:$B$152,2,FALSE()) -> Zinc Polymer | D165: =VLOOKUP(B165,Compounds!$A$3:$C$152,3,FALSE()) -> 5 | E165: T3_20 | F165: =VLOOKUP(E165,Compounds!$A$3:$B$152,2,FALSE()) -> Zinc Stannate | G165: T4_02 | H165: =VLOOKUP(G165,Compounds!$A$3:$B$152,2,FALSE()) -> Cubic Boron Nitride | I165: simple | K165: T3+T4->T5
A166: R164 | B166: T5_02 | C166: =VLOOKUP(B166,Compounds!$A$3:$B$152,2,FALSE()) -> Quantum Dot Suspension | D166: =VLOOKUP(B166,Compounds!$A$3:$C$152,3,FALSE()) -> 5 | E166: T3_20 | F166: =VLOOKUP(E166,Compounds!$A$3:$B$152,2,FALSE()) -> Zinc Stannate | G166: T4_03 | H166: =VLOOKUP(G166,Compounds!$A$3:$B$152,2,FALSE()) -> Pyrolytic Graphite | I166: simple | K166: T3+T4->T5
A167: R165 | B167: T5_06 | C167: =VLOOKUP(B167,Compounds!$A$3:$B$152,2,FALSE()) -> Topological Insulator | D167: =VLOOKUP(B167,Compounds!$A$3:$C$152,3,FALSE()) -> 5 | E167: T3_21 | F167: =VLOOKUP(E167,Compounds!$A$3:$B$152,2,FALSE()) -> Tungsten Bronze | G167: T4_15 | H167: =VLOOKUP(G167,Compounds!$A$3:$B$152,2,FALSE()) -> Thermoelectric Bismuthide | I167: simple | K167: T3+T4->T5
A168: R166 | B168: T5_08 | C168: =VLOOKUP(B168,Compounds!$A$3:$B$152,2,FALSE()) -> Photonic Crystal | D168: =VLOOKUP(B168,Compounds!$A$3:$C$152,3,FALSE()) -> 5 | E168: T3_22 | F168: =VLOOKUP(E168,Compounds!$A$3:$B$152,2,FALSE()) -> Vanadium Steel | G168: T4_04 | H168: =VLOOKUP(G168,Compounds!$A$3:$B$152,2,FALSE()) -> Fused Silica Composite | I168: simple | K168: T3+T4->T5
A169: R167 | B169: T5_10 | C169: =VLOOKUP(B169,Compounds!$A$3:$B$152,2,FALSE()) -> Plasmonic Composite | D169: =VLOOKUP(B169,Compounds!$A$3:$C$152,3,FALSE()) -> 5 | E169: T3_25 | F169: =VLOOKUP(E169,Compounds!$A$3:$B$152,2,FALSE()) -> Cerium Zirconate | G169: T4_12 | H169: =VLOOKUP(G169,Compounds!$A$3:$B$152,2,FALSE()) -> Metallic Glass | I169: simple | K169: T3+T4->T5
A170: R168 | B170: T5_15 | C170: =VLOOKUP(B170,Compounds!$A$3:$B$152,2,FALSE()) -> Borophene Sheet | D170: =VLOOKUP(B170,Compounds!$A$3:$C$152,3,FALSE()) -> 5 | E170: T3_26 | F170: =VLOOKUP(E170,Compounds!$A$3:$B$152,2,FALSE()) -> Calcium Hexaboride | G170: T4_05 | H170: =VLOOKUP(G170,Compounds!$A$3:$B$152,2,FALSE()) -> Amorphous Ferrosilicon | I170: simple | K170: T3+T4->T5
... A182: R180 | B182: T5_20 | C182: =VLOOKUP(B182,Compounds!$A$3:$B$152,2,FALSE()) -> Ionic Liquid Crystal | D182: =VLOOKUP(B182,Compounds!$A$3:$C$152,3,FALSE()) -> 5 | E182: T3_19 | F182: =VLOOKUP(E182,Compounds!$A$3:$B$152,2,FALSE()) -> Strontium Ferrite | G182: T4_19 | H182: =VLOOKUP(G182,Compounds!$A$3:$B$152,2,FALSE()) -> Dielectric Ceramite | I182: simple | K182: T3+T4->T5
A183: R181 | B183: T5_03 | C183: =VLOOKUP(B183,Compounds!$A$3:$B$152,2,FALSE()) -> Graphene Lattice | D183: =VLOOKUP(B183,Compounds!$A$3:$C$152,3,FALSE()) -> 5 | E183: T3_21 | F183: =VLOOKUP(E183,Compounds!$A$3:$B$152,2,FALSE()) -> Tungsten Bronze | G183: T4_21 | H183: =VLOOKUP(G183,Compounds!$A$3:$B$152,2,FALSE()) -> Refractory Carbide | I183: variable-primary | J183: V5_01 | K183: T3+T4->T5
A184: R182 | B184: T5_04 | C184: =VLOOKUP(B184,Compounds!$A$3:$B$152,2,FALSE()) -> Carbon Nanotube Array | D184: =VLOOKUP(B184,Compounds!$A$3:$C$152,3,FALSE()) -> 5 | E184: T3_21 | F184: =VLOOKUP(E184,Compounds!$A$3:$B$152,2,FALSE()) -> Tungsten Bronze | G184: T4_21 | H184: =VLOOKUP(G184,Compounds!$A$3:$B$152,2,FALSE()) -> Refractory Carbide | I184: variable-alternate | J184: V5_01 | K184: T3+T4->T5
A185: R183 | B185: T5_05 | C185: =VLOOKUP(B185,Compounds!$A$3:$B$152,2,FALSE()) -> Metamaterial Substrate | D185: =VLOOKUP(B185,Compounds!$A$3:$C$152,3,FALSE()) -> 5 | E185: T3_22 | F185: =VLOOKUP(E185,Compounds!$A$3:$B$152,2,FALSE()) -> Vanadium Steel | G185: T4_22 | H185: =VLOOKUP(G185,Compounds!$A$3:$B$152,2,FALSE()) -> Conductive Polymer Base | I185: variable-primary | J185: V5_02 | K185: T3+T4->T5
A186: R184 | B186: T5_07 | C186: =VLOOKUP(B186,Compounds!$A$3:$B$152,2,FALSE()) -> Superfluid Matrix | D186: =VLOOKUP(B186,Compounds!$A$3:$C$152,3,FALSE()) -> 5 | E186: T3_22 | F186: =VLOOKUP(E186,Compounds!$A$3:$B$152,2,FALSE()) -> Vanadium Steel | G186: T4_22 | H186: =VLOOKUP(G186,Compounds!$A$3:$B$152,2,FALSE()) -> Conductive Polymer Base | I186: variable-alternate | J186: V5_02 | K186: T3+T4->T5
A187: R185 | B187: T5_11 | C187: =VLOOKUP(B187,Compounds!$A$3:$B$152,2,FALSE()) -> Bose Condensate Gel | D187: =VLOOKUP(B187,Compounds!$A$3:$C$152,3,FALSE()) -> 5 | E187: T3_23 | F187: =VLOOKUP(E187,Compounds!$A$3:$B$152,2,FALSE()) -> Cobalt Ferrite | G187: T4_23 | H187: =VLOOKUP(G187,Compounds!$A$3:$B$152,2,FALSE()) -> Magnetocaloric Alloy | I187: variable-primary | J187: V5_03 | K187: T3+T4->T5
A188: R186 | B188: T5_12 | C188: =VLOOKUP(B188,Compounds!$A$3:$B$152,2,FALSE()) -> Programmable Matter Seed | D188: =VLOOKUP(B188,Compounds!$A$3:$C$152,3,FALSE()) -> 5 | E188: T3_23 | F188: =VLOOKUP(E188,Compounds!$A$3:$B$152,2,FALSE()) -> Cobalt Ferrite | G188: T4_23 | H188: =VLOOKUP(G188,Compounds!$A$3:$B$152,2,FALSE()) -> Magnetocaloric Alloy | I188: variable-alternate | J188: V5_03 | K188: T3+T4->T5
A189: R187 | B189: T5_13 | C189: =VLOOKUP(B189,Compounds!$A$3:$B$152,2,FALSE()) -> Self-Healing Polymer | D189: =VLOOKUP(B189,Compounds!$A$3:$C$152,3,FALSE()) -> 5 | E189: T3_24 | F189: =VLOOKUP(E189,Compounds!$A$3:$B$152,2,FALSE()) -> Nickel-Titanium Ingot | G189: T4_24 | H189: =VLOOKUP(G189,Compounds!$A$3:$B$152,2,FALSE()) -> Catalytic Vanadia | I189: variable-primary | J189: V5_04 | K189: T3+T4->T5
A190: R188 | B190: T5_14 | C190: =VLOOKUP(B190,Compounds!$A$3:$B$152,2,FALSE()) -> Diamond Nanothread | D190: =VLOOKUP(B190,Compounds!$A$3:$C$152,3,FALSE()) -> 5 | E190: T3_24 | F190: =VLOOKUP(E190,Compounds!$A$3:$B$152,2,FALSE()) -> Nickel-Titanium Ingot | G190: T4_24 | H190: =VLOOKUP(G190,Compounds!$A$3:$B$152,2,FALSE()) -> Catalytic Vanadia | I190: variable-alternate | J190: V5_04 | K190: T3+T4->T5
A191: R189 | B191: T5_01 | C191: =VLOOKUP(B191,Compounds!$A$3:$B$152,2,FALSE()) -> Zinc Polymer | D191: =VLOOKUP(B191,Compounds!$A$3:$C$152,3,FALSE()) -> 5 | E191: T3_20 | F191: =VLOOKUP(E191,Compounds!$A$3:$B$152,2,FALSE()) -> Zinc Stannate | G191: T4_25 | H191: =VLOOKUP(G191,Compounds!$A$3:$B$152,2,FALSE()) -> Hard Anodize Composite | I191: simple | K191: T3+T4->T5
A192: R190 | B192: T5_02 | C192: =VLOOKUP(B192,Compounds!$A$3:$B$152,2,FALSE()) -> Quantum Dot Suspension | D192: =VLOOKUP(B192,Compounds!$A$3:$C$152,3,FALSE()) -> 5 | E192: T3_20 | F192: =VLOOKUP(E192,Compounds!$A$3:$B$152,2,FALSE()) -> Zinc Stannate | G192: T4_01 | H192: =VLOOKUP(G192,Compounds!$A$3:$B$152,2,FALSE()) -> Synthetic Corundum | I192: simple | K192: T3+T4->T5
A193: R191 | B193: T6_01 | C193: =VLOOKUP(B193,Compounds!$A$3:$B$152,2,FALSE()) -> Stabilized Muonium | D193: =VLOOKUP(B193,Compounds!$A$3:$C$152,3,FALSE()) -> 6 | E193: T4_02 | F193: =VLOOKUP(E193,Compounds!$A$3:$B$152,2,FALSE()) -> Cubic Boron Nitride | G193: T5_01 | H193: =VLOOKUP(G193,Compounds!$A$3:$B$152,2,FALSE()) -> Zinc Polymer | I193: simple | K193: T4+T5->T6
A194: R192 | B194: T6_02 | C194: =VLOOKUP(B194,Compounds!$A$3:$B$152,2,FALSE()) -> Coherent Plasma Lattice | D194: =VLOOKUP(B194,Compounds!$A$3:$C$152,3,FALSE()) -> 6 | E194: T4_03 | F194: =VLOOKUP(E194,Compounds!$A$3:$B$152,2,FALSE()) -> Pyrolytic Graphite | G194: T5_02 | H194: =VLOOKUP(G194,Compounds!$A$3:$B$152,2,FALSE()) -> Quantum Dot Suspension | I194: simple | K194: T4+T5->T6
A195: R193 | B195: T6_03 | C195: =VLOOKUP(B195,Compounds!$A$3:$B$152,2,FALSE()) -> Isochronal Lattice | D195: =VLOOKUP(B195,Compounds!$A$3:$C$152,3,FALSE()) -> 6 | E195: T4_04 | F195: =VLOOKUP(E195,Compounds!$A$3:$B$152,2,FALSE()) -> Fused Silica Composite | G195: T5_03 | H195: =VLOOKUP(G195,Compounds!$A$3:$B$152,2,FALSE()) -> Graphene Lattice | I195: simple | K195: T4+T5->T6
A196: R194 | B196: T6_04 | C196: =VLOOKUP(B196,Compounds!$A$3:$B$152,2,FALSE()) -> Vacuum-Phase Crystal | D196: =VLOOKUP(B196,Compounds!$A$3:$C$152,3,FALSE()) -> 6 | E196: T4_05 | F196: =VLOOKUP(E196,Compounds!$A$3:$B$152,2,FALSE()) -> Amorphous Ferrosilicon | G196: T5_04 | H196: =VLOOKUP(G196,Compounds!$A$3:$B$152,2,FALSE()) -> Carbon Nanotube Array | I196: simple | K196: T4+T5->T6
A197: R195 | B197: T6_05 | C197: =VLOOKUP(B197,Compounds!$A$3:$B$152,2,FALSE()) -> Chronostable Isotope | D197: =VLOOKUP(B197,Compounds!$A$3:$C$152,3,FALSE()) -> 6 | E197: T4_06 | F197: =VLOOKUP(E197,Compounds!$A$3:$B$152,2,FALSE()) -> Single-Crystal Sapphire | G197: T5_05 | H197: =VLOOKUP(G197,Compounds!$A$3:$B$152,2,FALSE()) -> Metamaterial Substrate | I197: simple | K197: T4+T5->T6
A198: R196 | B198: T6_06 | C198: =VLOOKUP(B198,Compounds!$A$3:$B$152,2,FALSE()) -> Dark Lattice Composite | D198: =VLOOKUP(B198,Compounds!$A$3:$C$152,3,FALSE()) -> 6 | E198: T4_07 | F198: =VLOOKUP(E198,Compounds!$A$3:$B$152,2,FALSE()) -> Stabilized Zirconia | G198: T5_06 | H198: =VLOOKUP(G198,Compounds!$A$3:$B$152,2,FALSE()) -> Topological Insulator | I198: simple | K198: T4+T5->T6
A199: R197 | B199: T6_07 | C199: =VLOOKUP(B199,Compounds!$A$3:$B$152,2,FALSE()) -> Zero-Point Substrate | D199: =VLOOKUP(B199,Compounds!$A$3:$C$152,3,FALSE()) -> 6 | E199: T5_07 | F199: =VLOOKUP(E199,Compounds!$A$3:$B$152,2,FALSE()) -> Superfluid Matrix | G199: T5_08 | H199: =VLOOKUP(G199,Compounds!$A$3:$B$152,2,FALSE()) -> Photonic Crystal | I199: simple | K199: T5+T5->T6
A200: R198 | B200: T6_08 | C200: =VLOOKUP(B200,Compounds!$A$3:$B$152,2,FALSE()) -> Entangled Matrix | D200: =VLOOKUP(B200,Compounds!$A$3:$C$152,3,FALSE()) -> 6 | E200: T4_08 | F200: =VLOOKUP(E200,Compounds!$A$3:$B$152,2,FALSE()) -> Photonic Silica | G200: T5_09 | H200: =VLOOKUP(G200,Compounds!$A$3:$B$152,2,FALSE()) -> Spintronic Alloy | I200: simple | K200: T4+T5->T6
A201: R199 | B201: T6_09 | C201: =VLOOKUP(B201,Compounds!$A$3:$B$152,2,FALSE()) -> Femtosecond Glass | D201: =VLOOKUP(B201,Compounds!$A$3:$C$152,3,FALSE()) -> 6 | E201: T5_10 | F201: =VLOOKUP(E201,Compounds!$A$3:$B$152,2,FALSE()) -> Plasmonic Composite | G201: T5_11 | H201: =VLOOKUP(G201,Compounds!$A$3:$B$152,2,FALSE()) -> Bose Condensate Gel | I201: simple | K201: T5+T5->T6
A202: R200 | B202: T6_10 | C202: =VLOOKUP(B202,Compounds!$A$3:$B$152,2,FALSE()) -> Degenerate Matter Pellet | D202: =VLOOKUP(B202,Compounds!$A$3:$C$152,3,FALSE()) -> 6 | E202: T4_09 | F202: =VLOOKUP(E202,Compounds!$A$3:$B$152,2,FALSE()) -> Superconducting Niobate | G202: T5_12 | H202: =VLOOKUP(G202,Compounds!$A$3:$B$152,2,FALSE()) -> Programmable Matter Seed | I202: simple | K202: T4+T5->T6
... A207: R205 | B207: T6_15 | C207: =VLOOKUP(B207,Compounds!$A$3:$B$152,2,FALSE()) -> Picoscale Architect | D207: =VLOOKUP(B207,Compounds!$A$3:$C$152,3,FALSE()) -> 6 | E207: T5_19 | F207: =VLOOKUP(E207,Compounds!$A$3:$B$152,2,FALSE()) -> Auxetic Foam | G207: T5_20 | H207: =VLOOKUP(G207,Compounds!$A$3:$B$152,2,FALSE()) -> Ionic Liquid Crystal | I207: simple | K207: T5+T5->T6

Sheet Exotics
A1: EXOTIC SEED TABLE — all 120 T6+T6 combinations (doc §23). This table IS the procedural generator's output, shipped as data: deterministic, collision-free, server does a lookup on first completion.
A3: Exotic ID | B3: Input A | C3: Input A name | D3: Input B | E3: Input B name | F3: Exotic name | G3: Initial value | H3: Claim bonus (3x initial) | I3: Floor value (25%) | K3: Weekly dividend (all Exotics):
A4: EX_001 | B4: T6_01 | C4: =VLOOKUP(B4,Compounds!$A$3:$B$152,2,FALSE()) -> Stabilized Muonium | D4: T6_01 | E4: =VLOOKUP(D4,Compounds!$A$3:$B$152,2,FALSE()) -> Stabilized Muonium | F4: Trans-chromate IX | G4: 376000 | H4: =G4*3 -> 1128000 | I4: =G4*0.25 -> 94000 | K4: 200000
A5: EX_002 | B5: T6_01 | C5: =VLOOKUP(B5,Compounds!$A$3:$B$152,2,FALSE()) -> Stabilized Muonium | D5: T6_02 | E5: =VLOOKUP(D5,Compounds!$A$3:$B$152,2,FALSE()) -> Coherent Plasma Lattice | F5: Meta-titanate Prime | G5: 495000 | H5: =G5*3 -> 1485000 | I5: =G5*0.25 -> 123750
A6: EX_003 | B6: T6_01 | C6: =VLOOKUP(B6,Compounds!$A$3:$B$152,2,FALSE()) -> Stabilized Muonium | D6: T6_03 | E6: =VLOOKUP(D6,Compounds!$A$3:$B$152,2,FALSE()) -> Isochronal Lattice | F6: Hyper-zirconate Omega | G6: 453000 | H6: =G6*3 -> 1359000 | I6: =G6*0.25 -> 113250 | K6: Doc §23 example names occupy real slots:
A7: EX_004 | B7: T6_01 | C7: =VLOOKUP(B7,Compounds!$A$3:$B$152,2,FALSE()) -> Stabilized Muonium | D7: T6_04 | E7: =VLOOKUP(D7,Compounds!$A$3:$B$152,2,FALSE()) -> Vacuum-Phase Crystal | F7: Para-vanadate X | G7: 664000 | H7: =G7*3 -> 1992000 | I7: =G7*0.25 -> 166000 | K7: Trans-chromate IX, Meta-titanate Prime, Hyper-zirconate Omega
A8: EX_005 | B8: T6_01 | C8: =VLOOKUP(B8,Compounds!$A$3:$B$152,2,FALSE()) -> Stabilized Muonium | D8: T6_05 | E8: =VLOOKUP(D8,Compounds!$A$3:$B$152,2,FALSE()) -> Chronostable Isotope | F8: Xeno-borate X | G8: 464000 | H8: =G8*3 -> 1392000 | I8: =G8*0.25 -> 116000
A9: EX_006 | B9: T6_01 | C9: =VLOOKUP(B9,Compounds!$A$3:$B$152,2,FALSE()) -> Stabilized Muonium | D9: T6_06 | E9: =VLOOKUP(D9,Compounds!$A$3:$B$152,2,FALSE()) -> Dark Lattice Composite | F9: Para-titanate Helix | G9: 631000 | H9: =G9*3 -> 1893000 | I9: =G9*0.25 -> 157750 | K9: Runtime stats (all Exotics, doc §23/§5):
A10: EX_007 | B10: T6_01 | C10: =VLOOKUP(B10,Compounds!$A$3:$B$152,2,FALSE()) -> Stabilized Muonium | D10: T6_07 | E10: =VLOOKUP(D10,Compounds!$A$3:$B$152,2,FALSE()) -> Zero-Point Substrate | F10: Iso-titanate Prime | G10: 710000 | H10: =G10*3 -> 2130000 | I10: =G10*0.25 -> 177500 | K10: Synthesis: 24h Joint Synthesis only
A11: EX_008 | B11: T6_01 | C11: =VLOOKUP(B11,Compounds!$A$3:$B$152,2,FALSE()) -> Stabilized Muonium | D11: T6_08 | E11: =VLOOKUP(D11,Compounds!$A$3:$B$152,2,FALSE()) -> Entangled Matrix | F11: Anti-vanadate II | G11: 571000 | H11: =G11*3 -> 1713000 | I11: =G11*0.25 -> 142750 | K11: Passive income P/min: | L11: 60
A12: EX_009 | B12: T6_01 | C12: =VLOOKUP(B12,Compounds!$A$3:$B$152,2,FALSE()) -> Stabilized Muonium | D12: T6_09 | E12: =VLOOKUP(D12,Compounds!$A$3:$B$152,2,FALSE()) -> Femtosecond Glass | F12: Meta-ferrate II | G12: 526000 | H12: =G12*3 -> 1578000 | I12: =G12*0.25 -> 131500
A13: EX_010 | B13: T6_01 | C13: =VLOOKUP(B13,Compounds!$A$3:$B$152,2,FALSE()) -> Stabilized Muonium | D13: T6_10 | E13: =VLOOKUP(D13,Compounds!$A$3:$B$152,2,FALSE()) -> Degenerate Matter Pellet | F13: Neo-borate Omega | G13: 441000 | H13: =G13*3 -> 1323000 | I13: =G13*0.25 -> 110250
A14: EX_011 | B14: T6_01 | C14: =VLOOKUP(B14,Compounds!$A$3:$B$152,2,FALSE()) -> Stabilized Muonium | D14: T6_11 | E14: =VLOOKUP(D14,Compounds!$A$3:$B$152,2,FALSE()) -> Hyperdense Ceramic | F14: Hyper-borate IX | G14: 292000 | H14: =G14*3 -> 876000 | I14: =G14*0.25 -> 73000
A15: EX_012 | B15: T6_01 | C15: =VLOOKUP(B15,Compounds!$A$3:$B$152,2,FALSE()) -> Stabilized Muonium | D15: T6_12 | E15: =VLOOKUP(D15,Compounds!$A$3:$B$152,2,FALSE()) -> Singularity Alloy | F15: Poly-silicate VIII | G15: 302000 | H15: =G15*3 -> 906000 | I15: =G15*0.25 -> 75500
A16: EX_013 | B16: T6_01 | C16: =VLOOKUP(B16,Compounds!$A$3:$B$152,2,FALSE()) -> Stabilized Muonium | D16: T6_13 | E16: =VLOOKUP(D16,Compounds!$A$3:$B$152,2,FALSE()) -> Antiferric Compound | F16: Xeno-zirconate Prime | G16: 492000 | H16: =G16*3 -> 1476000 | I16: =G16*0.25 -> 123000
A17: EX_014 | B17: T6_01 | C17: =VLOOKUP(B17,Compounds!$A$3:$B$152,2,FALSE()) -> Stabilized Muonium | D17: T6_14 | E17: =VLOOKUP(D17,Compounds!$A$3:$B$152,2,FALSE()) -> Quantum Foam Stabilizate | F17: Ultra-borate V | G17: 299000 | H17: =G17*3 -> 897000 | I17: =G17*0.25 -> 74750
A18: EX_015 | B18: T6_01 | C18: =VLOOKUP(B18,Compounds!$A$3:$B$152,2,FALSE()) -> Stabilized Muonium | D18: T6_15 | E18: =VLOOKUP(D18,Compounds!$A$3:$B$152,2,FALSE()) -> Picoscale Architect | F18: Hyper-tungstate Alpha | G18: 545000 | H18: =G18*3 -> 1635000 | I18: =G18*0.25 -> 136250
A19: EX_016 | B19: T6_02 | C19: =VLOOKUP(B19,Compounds!$A$3:$B$152,2,FALSE()) -> Coherent Plasma Lattice | D19: T6_02 | E19: =VLOOKUP(D19,Compounds!$A$3:$B$152,2,FALSE()) -> Coherent Plasma Lattice | F19: Poly-vanadate II | G19: 353000 | H19: =G19*3 -> 1059000 | I19: =G19*0.25 -> 88250
A20: EX_017 | B20: T6_02 | C20: =VLOOKUP(B20,Compounds!$A$3:$B$152,2,FALSE()) -> Coherent Plasma Lattice | D20: T6_03 | E20: =VLOOKUP(D20,Compounds!$A$3:$B$152,2,FALSE()) -> Isochronal Lattice | F20: Meta-zirconate Helix | G20: 555000 | H20: =G20*3 -> 1665000 | I20: =G20*0.25 -> 138750
A21: EX_018 | B21: T6_02 | C21: =VLOOKUP(B21,Compounds!$A$3:$B$152,2,FALSE()) -> Coherent Plasma Lattice | D21: T6_04 | E21: =VLOOKUP(D21,Compounds!$A$3:$B$152,2,FALSE()) -> Vacuum-Phase Crystal | F21: Anti-chromate Prime | G21: 787000 | H21: =G21*3 -> 2361000 | I21: =G21*0.25 -> 196750
A22: EX_019 | B22: T6_02 | C22: =VLOOKUP(B22,Compounds!$A$3:$B$152,2,FALSE()) -> Coherent Plasma Lattice | D22: T6_05 | E22: =VLOOKUP(D22,Compounds!$A$3:$B$152,2,FALSE()) -> Chronostable Isotope | F22: Anti-silicate I | G22: 704000 | H22: =G22*3 -> 2112000 | I22: =G22*0.25 -> 176000
A23: EX_020 | B23: T6_02 | C23: =VLOOKUP(B23,Compounds!$A$3:$B$152,2,FALSE()) -> Coherent Plasma Lattice | D23: T6_06 | E23: =VLOOKUP(D23,Compounds!$A$3:$B$152,2,FALSE()) -> Dark Lattice Composite | F23: Hyper-titanate VIII | G23: 462000 | H23: =G23*3 -> 1386000 | I23: =G23*0.25 -> 115500
... A123: EX_120 | B123: T6_15 | C123: =VLOOKUP(B123,Compounds!$A$3:$B$152,2,FALSE()) -> Picoscale Architect | D123: T6_15 | E123: =VLOOKUP(D123,Compounds!$A$3:$B$152,2,FALSE()) -> Picoscale Architect | F123: Neo-niobate IV | G123: 296000 | H123: =G123*3 -> 888000 | I123: =G123*0.25 -> 74000

Sheet Event_Compounds
A1: CASCADE PROTOCOL EVENT COMPOUNDS (doc §29) — blueprint recipes, pairs verified non-colliding with all base recipes
A2: ID | B2: Name | C2: Tier | D2: Time (min) | E2: Base value | F2: Blueprint cost (Flux) | G2: Input 1 | H2: Input 1 name | I2: Input 2 | J2: Input 2 name
A3: EV_01 | B3: Cascade Trace | C3: 2 | D3: 12 | E3: 120 | F3: 50 | G3: T1_01 | H3: =VLOOKUP(G3,Compounds!$A$3:$B$152,2,FALSE()) -> Sodium Chloride | I3: T1_05 | J3: =VLOOKUP(I3,Compounds!$A$3:$B$152,2,FALSE()) -> Potassium Iodide
A4: EV_02 | B4: Cascade Alpha | C4: 3 | D4: 45 | E4: 550 | F4: 300 | G4: T1_10 | H4: =VLOOKUP(G4,Compounds!$A$3:$B$152,2,FALSE()) -> Titanium Dioxide | I4: T2_08 | J4: =VLOOKUP(I4,Compounds!$A$3:$B$152,2,FALSE()) -> Barium Titanate
A5: EV_03 | B5: Cascade Beta | C5: 3 | D5: 45 | E5: 620 | F5: 300 | G5: T2_03 | H5: =VLOOKUP(G5,Compounds!$A$3:$B$152,2,FALSE()) -> Calcium Silicate | I5: T2_17 | J5: =VLOOKUP(I5,Compounds!$A$3:$B$152,2,FALSE()) -> Potassium Silicate
A6: EV_04 | B6: Cascade Gamma | C6: 4 | D6: 180 | E6: 2800 | F6: 1200 | G6: T2_01 | H6: =VLOOKUP(G6,Compounds!$A$3:$B$152,2,FALSE()) -> Zinc Titanate | I6: T3_04 | J6: =VLOOKUP(I6,Compounds!$A$3:$B$152,2,FALSE()) -> Titanium Aluminide
A7: EV_05 | B7: Cascade Delta | C7: 4 | D7: 180 | E7: 3100 | F7: 1200 | G7: T3_02 | H7: =VLOOKUP(G7,Compounds!$A$3:$B$152,2,FALSE()) -> Ferrochrome Alloy | I7: T3_13 | J7: =VLOOKUP(I7,Compounds!$A$3:$B$152,2,FALSE()) -> Chromium Silicide
A8: EV_06 | B8: Cascade Epsilon | C8: 5 | D8: 480 | E8: 14000 | F8: 4000 | G8: T3_01 | H8: =VLOOKUP(G8,Compounds!$A$3:$B$152,2,FALSE()) -> Borosilicate Glass | I8: T4_04 | J8: =VLOOKUP(I8,Compounds!$A$3:$B$152,2,FALSE()) -> Fused Silica Composite
A9: EV_07 | B9: Cascade Omega | C9: 5 | D9: 480 | E9: 17000 | F9: 4000 | G9: T3_24 | H9: =VLOOKUP(G9,Compounds!$A$3:$B$152,2,FALSE()) -> Nickel-Titanium Ingot | I9: T4_13 | J9: =VLOOKUP(I9,Compounds!$A$3:$B$152,2,FALSE()) -> Shape-Memory Nitinol
A11: Cascade Trace inputs are two STARTER compounds — a day-one player can blueprint and synthesize it (doc §29). Cascade-series compounds are event fiction; element conservation deliberately not applied.

Sheet Validation
A1: VALIDATION — live formula checks + Python-verified structural checks
A3: Check | B3: Target (doc) | C3: Actual | D3: Verdict
A4: T1 compound count | B4: 30 | C4: =COUNTIF(Compounds!$C$3:$C$152,1) -> 30 | D4: =IF(C4=B4,"PASS","FAIL") -> PASS
A5: T2 compound count | B5: 30 | C5: =COUNTIF(Compounds!$C$3:$C$152,2) -> 30 | D5: =IF(C5=B5,"PASS","FAIL") -> PASS
A6: T3 compound count | B6: 30 | C6: =COUNTIF(Compounds!$C$3:$C$152,3) -> 30 | D6: =IF(C6=B6,"PASS","FAIL") -> PASS
A7: T4 compound count | B7: 25 | C7: =COUNTIF(Compounds!$C$3:$C$152,4) -> 25 | D7: =IF(C7=B7,"PASS","FAIL") -> PASS
A8: T5 compound count | B8: 20 | C8: =COUNTIF(Compounds!$C$3:$C$152,5) -> 20 | D8: =IF(C8=B8,"PASS","FAIL") -> PASS
A9: T6 compound count | B9: 15 | C9: =COUNTIF(Compounds!$C$3:$C$152,6) -> 15 | D9: =IF(C9=B9,"PASS","FAIL") -> PASS
A10: Recipes -> T1 results | B10: 25 | C10: =COUNTIF(Recipes!$D$3:$D$207,1) -> 25 | D10: =IF(C10=B10,"PASS","FAIL") -> PASS
A11: Recipes -> T2 results | B11: 40 | C11: =COUNTIF(Recipes!$D$3:$D$207,2) -> 40 | D11: =IF(C11=B11,"PASS","FAIL") -> PASS
A12: Recipes -> T3 results | B12: 50 | C12: =COUNTIF(Recipes!$D$3:$D$207,3) -> 50 | D12: =IF(C12=B12,"PASS","FAIL") -> PASS
A13: Recipes -> T4 results | B13: 45 | C13: =COUNTIF(Recipes!$D$3:$D$207,4) -> 45 | D13: =IF(C13=B13,"PASS","FAIL") -> PASS
A14: Recipes -> T5 results | B14: 30 | C14: =COUNTIF(Recipes!$D$3:$D$207,5) -> 30 | D14: =IF(C14=B14,"PASS","FAIL") -> PASS
A15: Recipes -> T6 results | B15: 15 | C15: =COUNTIF(Recipes!$D$3:$D$207,6) -> 15 | D15: =IF(C15=B15,"PASS","FAIL") -> PASS
A16: Total recipe mappings | B16: 205 | C16: =COUNTA(Recipes!$A$3:$A$207) -> 205 | D16: =IF(C16=B16,"PASS","FAIL") -> PASS
A17: T1+T2->T3 (econ model: 30) | B17: 30 | C17: =COUNTIF(Recipes!$K$3:$K$207,"T1+T2->T3") -> 30 | D17: =IF(C17=B17,"PASS","FAIL") -> PASS
A18: T2+T2->T3 (econ model: 20) | B18: 20 | C18: =COUNTIF(Recipes!$K$3:$K$207,"T2+T2->T3") -> 20 | D18: =IF(C18=B18,"PASS","FAIL") -> PASS
A19: T2+T3->T4 (econ model: 27) | B19: 27 | C19: =COUNTIF(Recipes!$K$3:$K$207,"T2+T3->T4") -> 27 | D19: =IF(C19=B19,"PASS","FAIL") -> PASS
A20: T3+T3->T4 (econ model: 18) | B20: 18 | C20: =COUNTIF(Recipes!$K$3:$K$207,"T3+T3->T4") -> 18 | D20: =IF(C20=B20,"PASS","FAIL") -> PASS
A21: T3+T4->T5 (econ model: 30) | B21: 30 | C21: =COUNTIF(Recipes!$K$3:$K$207,"T3+T4->T5") -> 30 | D21: =IF(C21=B21,"PASS","FAIL") -> PASS
A22: Variable-alternate mappings (17 pairs) | B22: 17 | C22: =COUNTIF(Recipes!$I$3:$I$207,"variable-alternate") -> 17 | D22: =IF(C22=B22,"PASS","FAIL") -> PASS
A23: Exotic seed entries | B23: 120 | C23: =COUNTA(Exotics!$A$4:$A$123) -> 120 | D23: =IF(C23=B23,"PASS","FAIL") -> PASS
A24: T1 values within doc range | B24: TRUE | C24: =AND(MIN(Compounds!$F$3:$F$32)>=Tier_Constants!D3,MAX(Compounds!$F$3:$F$32)<=Tier_Constants!E3) -> TRUE | D24: =IF(C24=TRUE(),"PASS","FAIL") -> PASS
A25: T2 values within doc range | B25: TRUE | C25: =AND(MIN(Compounds!$F$33:$F$62)>=Tier_Constants!D4,MAX(Compounds!$F$33:$F$62)<=Tier_Constants!E4) -> TRUE | D25: =IF(C25=TRUE(),"PASS","FAIL") -> PASS
A26: T3 values within doc range | B26: TRUE | C26: =AND(MIN(Compounds!$F$63:$F$92)>=Tier_Constants!D5,MAX(Compounds!$F$63:$F$92)<=Tier_Constants!E5) -> TRUE | D26: =IF(C26=TRUE(),"PASS","FAIL") -> PASS
A27: T4 values within doc range | B27: TRUE | C27: =AND(MIN(Compounds!$F$93:$F$117)>=Tier_Constants!D6,MAX(Compounds!$F$93:$F$117)<=Tier_Constants!E6) -> TRUE | D27: =IF(C27=TRUE(),"PASS","FAIL") -> PASS
A28: T5 values within doc range | B28: TRUE | C28: =AND(MIN(Compounds!$F$118:$F$137)>=Tier_Constants!D7,MAX(Compounds!$F$118:$F$137)<=Tier_Constants!E7) -> TRUE | D28: =IF(C28=TRUE(),"PASS","FAIL") -> PASS
A29: T6 values within doc range | B29: TRUE | C29: =AND(MIN(Compounds!$F$138:$F$152)>=Tier_Constants!D8,MAX(Compounds!$F$138:$F$152)<=Tier_Constants!E8) -> TRUE | D29: =IF(C29=TRUE(),"PASS","FAIL") -> PASS
A30: Tier value separation | B30: TRUE | C30: =AND(MAX(Compounds!$F$3:$F$32)<MIN(Compounds!$F$33:$F$62),MAX(Compounds!$F$33:$F$62)<MIN(Compounds!$F$63:$F$92),MAX(Compounds!$F$63:$F$92)<MIN(Compounds!$F$93:$F$117),MAX(Compounds!$F$93:$F$117)<MIN(Compounds!$F$118:$F$137),MAX(Compounds!$F$118:$F$137)<MIN(Compounds!$F$138:$F$152)) -> TRUE | D30: =IF(C30=TRUE(),"PASS","FAIL") -> PASS
A31: Exotic values within 250k-800k | B31: TRUE | C31: =AND(MIN(Exotics!$G$4:$G$123)>=250000,MAX(Exotics!$G$4:$G$123)<=800000) -> TRUE | D31: =IF(C31=TRUE(),"PASS","FAIL") -> PASS
A33: PYTHON-VERIFIED STRUCTURAL CHECKS (gen_compounds_v2.py hard assertions, seed 92136505)
A34: ELEMENT CONSERVATION: every T2/T3/T4 recipe (and every element-keyed T5 recipe) draws all key elements from its inputs; anions and atmosphere (O/C/N/S/Cl/I/H/F) are facility process feeds — PASS | D34: PASS
A35: T1 element faucet: the 30 T1 compounds carry the game's entire 29-element palette; extraction is the only element source — PASS | D35: PASS
A36: T1 discovery pairs are analytical signatures (extraction-license unlocks, doc §6), shared-element preferred, strict discovery DAG — PASS | D36: PASS
A37: Reachability: all 150 compounds craftable via BFS from the 5 starters — PASS | D37: PASS
A38: Global pair uniqueness (variable pairs: exactly 2 mappings on 1 pair); 17 variable pairs = 15.7% of T3-T5 pairs (doc ~15%) — PASS | D38: PASS
A39: Variable pairs are polymorph couples: both variants element-covered by the same input pair — PASS | D39: PASS
A40: Tier legality of all 205 recipes; event pairs collide with zero base pairs — PASS | D40: PASS
A41: Exotics: 120 entries = all 105 mixed + 15 same-compound T6 pairs, names unique, doc example names at real slots — PASS | D41: PASS
A42: Input coverage: 100% of T1-T5 used as input >=1 time; T6 never an authored input (T6+T6 is the Exotic table) — PASS | D42: PASS
A43: Doc-required names present at correct tiers: 5 starters, Zinc Titanate (T2), Zinc Salt (T2), Zinc Polymer (T5), Cascade set — PASS | D43: PASS
A44: All 150 base names + 120 Exotic names unique — PASS | D44: PASS
A45: Event blueprint pairs are tier-legal for their printed tier (Trace T1+T1, Alpha/Beta T1+T2/T2+T2, Gamma/Delta T2+T3/T3+T3, Epsilon/Omega T3+T4) — asserted programmatically — PASS | D45: PASS
